Workbook

Sheet Overview
A1: 유비 | B1: LiuBei
A2: 관우 | B2: GuanYu
A3: 장비 | B3: ZhangFei
A4: 조운 | B4: ZhaoYun
A5: 황충 | B5: HuangZhong
A6: 제갈량 | B6: ZhugeLiang
A7: 조조 | B7: CaoCao
A8: 조인 | B8: CaoRen
A9: 하후돈 | B9: XiahouDun
A10: 장료 | B10: ZhangLiao
A11: 하후연 | B11: XiahouYuan
A12: 순욱 | B12: XunYu
... A28: 장달 | B28: ZhangDa

Sheet String
A1: # | B1: key | C1: kr | D1: en | E1: cn
A2: string | B2: string | C2: string | D2: string | E2: string
B3: BATTLESTAT_ATTACK_POWER | C3: 공격력 | D3: ATK | E3: 攻击力
B4: BATTLESTAT_ATTACK_SPEED | C4: 공격속도 | D4: A.SPD | E4: 攻击速度
B5: BATTLESTAT_BOSS_DAMAGE | C5: 보스피해량 | D5: BossDMG | E5: Boss伤害
B6: BATTLESTAT_COOLDOWN_RATE | C6: 쿨타임감소 | D6: Cooldown | E6: 冷却缩减
B7: BATTLESTAT_CRITICAL_DAMAGE | C7: 치명위력 | D7: Cri.DMG | E7: 暴击威力
B8: BATTLESTAT_CRITICAL_RATE | C8: 치명타율 | D8: Cri.Rate | E8: 暴击率
B9: BATTLESTAT_DEFENCE | C9: 방어력 | D9: DEF | E9: 防御力
B10: BATTLESTAT_HEALTH_MAX | C10: 체력 | D10: HP | E10: 生命值
B11: BATTLESTAT_LIFE_STEAL | C11: 체력흡수 | D11: Lifesteal | E11: 生命汲取
B12: BATTLESTAT_MOVE_SPEED | C12: 이동속도 | D12: M.SPD | E12: 移动速度
B13: BUTTON_BACK | C13: 돌아가기 | D13: BACK | E13: 返回
B14: BUTTON_CANCEL | C14: 취소 | D14: CANCEL | E14: 取消
... B75: CASTLE_TITLE | C75: 영지 | D75: Domain | E75: 领地
A76: chiefmilitaryadviser | B76: ="CHARACTER_POSITION_"&UPPER(A76) -> CHARACTER_POSITION_CHIEFMILITARYADVISER | C76: 군사중랑장 | D76: Chief Military Adviser | E76: 军师中郎将
A77: directorofthesecretariat | B77: ="CHARACTER_POSITION_"&UPPER(A77) -> CHARACTER_POSITION_DIRECTOROFTHESECRETARIAT | C77: 상서령 | D77: Secretariat Director | E77: 尚书令
A78: dragonfighter | B78: ="CHARACTER_POSITION_"&UPPER(A78) -> CHARACTER_POSITION_DRAGONFIGHTER | C78: 용의 전사 | D78: Dragon Warrior | E78: 龙之战士
A79: generaloftheleft | B79: ="CHARACTER_POSITION_"&UPPER(A79) -> CHARACTER_POSITION_GENERALOFTHELEFT | C79: 좌장군 | D79: General Left | E79: 左将军
A80: generaloftherear | B80: ="CHARACTER_POSITION_"&UPPER(A80) -> CHARACTER_POSITION_GENERALOFTHEREAR | C80: 후장군 | D80: General Rear | E80: 后将军
A81: generaloftheright | B81: ="CHARACTER_POSITION_"&UPPER(A81) -> CHARACTER_POSITION_GENERALOFTHERIGHT | C81: 우장군 | D81: General Right | E81: 右将军
A82: generalofthevanguard | B82: ="CHARACTER_POSITION_"&UPPER(A82) -> CHARACTER_POSITION_GENERALOFTHEVANGUARD | C82: 전장군 | D82: General Vanguard | E82: 前将军
A83: grandgeneral | B83: ="CHARACTER_POSITION_"&UPPER(A83) -> CHARACTER_POSITION_GRANDGENERAL | C83: 대장군 | D83: Grand General | E83: 大将军
A84: grandstrategist | B84: ="CHARACTER_POSITION_"&UPPER(A84) -> CHARACTER_POSITION_GRANDSTRATEGIST | C84: 군사 | D84: Grand Strategist | E84: 军师
A85: palaceassistantinspector | B85: ="CHARACTER_POSITION_"&UPPER(A85) -> CHARACTER_POSITION_PALACEASSISTANTINSPECTOR | C85: 어사중승 | D85: Vice Censor-in-Chief | E85: 御史中丞
A86: primeminister | B86: ="CHARACTER_POSITION_"&UPPER(A86) -> CHARACTER_POSITION_PRIMEMINISTER | C86: 승상 | D86: Prime Minister | E86: 丞相
A87: suppressesbandits | B87: ="CHARACTER_POSITION_"&UPPER(A87) -> CHARACTER_POSITION_SUPPRESSESBANDITS | C87: 탕구장군 | D87: Subduing General | E87: 荡寇将军
... A91: generalofthecavalry | B91: ="CHARACTER_POSITION_"&UPPER(A91) -> CHARACTER_POSITION_GENERALOFTHECAVALRY | C91: 편장군 | D91: Deputy General | E91: 偏将军
A92: chiefmilitaryadviser | B92: ="CHARACTER_POSITION_S_"&UPPER(A92) -> CHARACTER_POSITION_S_CHIEFMILITARYADVISER | C92: 군사중랑장 | D92: CMA | E92: 军师中郎将
A93: directorofthesecretariat | B93: ="CHARACTER_POSITION_S_"&UPPER(A93) -> CHARACTER_POSITION_S_DIRECTOROFTHESECRETARIAT | C93: 상서령 | D93: SEC DIR | E93: 尚书令
A94: dragonfighter | B94: ="CHARACTER_POSITION_S_"&UPPER(A94) -> CHARACTER_POSITION_S_DRAGONFIGHTER | C94: 용의 전사 | D94: DRG WAR | E94: 龙之战士
A95: generaloftheleft | B95: ="CHARACTER_POSITION_S_"&UPPER(A95) -> CHARACTER_POSITION_S_GENERALOFTHELEFT | C95: 좌장군 | D95: GEN.L | E95: 左将军
A96: generaloftherear | B96: ="CHARACTER_POSITION_S_"&UPPER(A96) -> CHARACTER_POSITION_S_GENERALOFTHEREAR | C96: 후장군 | D96: GEN.R | E96: 后将军
A97: generaloftheright | B97: ="CHARACTER_POSITION_S_"&UPPER(A97) -> CHARACTER_POSITION_S_GENERALOFTHERIGHT | C97: 우장군 | D97: GEN.RGT | E97: 右将军
A98: generalofthevanguard | B98: ="CHARACTER_POSITION_S_"&UPPER(A98) -> CHARACTER_POSITION_S_GENERALOFTHEVANGUARD | C98: 전장군 | D98: GEN.VAN | E98: 前将军
A99: grandgeneral | B99: ="CHARACTER_POSITION_S_"&UPPER(A99) -> CHARACTER_POSITION_S_GRANDGENERAL | C99: 대장군 | D99: G GEN | E99: 大将军
A100: grandstrategist | B100: ="CHARACTER_POSITION_S_"&UPPER(A100) -> CHARACTER_POSITION_S_GRANDSTRATEGIST | C100: 군사 | D100: G STRAT | E100: 军师
A101: palaceassistantinspector | B101: ="CHARACTER_POSITION_S_"&UPPER(A101) -> CHARACTER_POSITION_S_PALACEASSISTANTINSPECTOR | C101: 어사중승 | D101: VICE CEN | E101: 御史中丞
A102: primeminister | B102: ="CHARACTER_POSITION_S_"&UPPER(A102) -> CHARACTER_POSITION_S_PRIMEMINISTER | C102: 승상 | D102: PM | E102: 丞相
A103: suppressesbandits | B103: ="CHARACTER_POSITION_S_"&UPPER(A103) -> CHARACTER_POSITION_S_SUPPRESSESBANDITS | C103: 탕구장군 | D103: SUB G | E103: 荡寇将军
... A106: militarysima | B106: ="CHARACTER_POSITION_S_"&UPPER(A106) -> CHARACTER_POSITION_S_MILITARYSIMA | C106: 군사마 | D106: Q.MASTER | E106: 军师马
A107: generalofthemid | B107: ="CHARACTER_POSITION_S_"&UPPER(A107) -> CHARACTER_POSITION_S_GENERALOFTHEMID | C107: 진군장군
A108: generalofthecavalry | B108: ="CHARACTER_POSITION_S_"&UPPER(A108) -> CHARACTER_POSITION_S_GENERALOFTHECAVALRY | C108: 편장군 | D108: DEP G | E108: 偏将军
B109: COMPLETE | C109: 완료 | D109: Complete | E109: 完成
B110: COMPLETE_REWARD | C110: 획득완료 | D110: Claimed | E110: 已获得
B111: CONTENTS_MARKET_TAB_DAILY | C111: 일일상점 | D111: DAILY | E111: 每日商店
B112: CONTENTS_MARKET_TAB_DAILY_DESC | C112: 상품은 매일 정해진 시간에 초기화되며, 등급에 따라 등장할 확률이 구분됩니다.<br><size=85%>일반 : 50%<pos=200>정예 28%<pos=400>명장 : 14%<br>영웅 : 6%<pos=200>전설 : 2%</size> | D112: Goods reset at a set time each day, and the chance of appearing differs by grade.<br><size=85%>N: 50%<pos=200>E: 28%<pos=400>G: 14%<br>H: 6%<pos=200>L: 2%</size> | E112: 商品每日在固定时间刷新，出现概率依品阶区分。<br><size=85%>普通：50%<pos=200>精锐：28%<pos=400>名将：14%<br>英雄：6%<pos=200>传说：2%</size>
B113: CONTENTS_MARKET_TAB_RAID | C113: 파편상점 | D113: SHARD | E113: 碎片商店
B114: CONTENTS_MARKET_TAB_RAID_DESC | C114: 레이드 처치 후 포인트를 획득하여 원하는 아이템으로 교환하세요!<br>*종료 기간까지 포인트를 사용하지 않을 경우 포인트는 소멸됩니다. | D114: Defeat raid bosses to earn points and trade them for the items you want!<br>*Any points left unspent by the end of the period will be lost. | E114: 讨伐首领获得积分，兑换你想要的道具！<br>*若在结束期限前未使用积分，积分将会消失。
B115: CONTENTS_MARKET_TAB_TOURNAMENT | C115: 비무상점 | D115: TOURN | E115: 比武商店
B116: CONTENTS_MARKET_TAB_TOURNAMENT_DESC | C116: 비무대회 참여 후 포인트를 획득하여 원하는 아이템으로 교환하세요! | D116: Take part in the Tournament to earn points and trade them for the items you want! | E116: 参加比武大会获得积分，兑换你想要的道具！
B117: CORESTAT_CHARISMA | C117: 매력 | D117: CHA | E117: 魅力
B118: CORESTAT_INTELLECT | C118: 지력 | D118: INT | E118: 智力
B119: CORESTAT_LEADERSHIP | C119: 통솔 | D119: LEA | E119: 统率
B120: CORESTAT_POLITICS | C120: 정치 | D120: POL | E120: 政治
... B156: MENU_EXIT | C156: 나가기 | D156: EXIT | E156: 退出
A157: INVENTORY | B157: ="MENU_"&A157 -> MENU_INVENTORY | C157: 보관함 | D157: INVEN | E157: 仓库
A158: NOTI | B158: ="MENU_"&A158 -> MENU_NOTI | C158: 공지사항 | D158: NOTICE | E158: 公告
A159: PASS | B159: ="MENU_"&A159 -> MENU_PASS | C159: 논공행상 | D159: MERITS | E159: 论功行赏
A160: POST | B160: ="MENU_"&A160 -> MENU_POST | C160: 우편함 | D160: POST | E160: 邮箱
A161: QUEST | B161: ="MENU_"&A161 -> MENU_QUEST | C161: 임무 | D161: QUEST | E161: 任务
B162: MENU_REBIRTH | C162: 회귀 | D162: REWIND | E162: 轮回
B163: MENU_SETTING | C163: 설정 | D163: CONFIG | E163: 设置
B164: PEROID_TYPE_DAILY | C164: 일일 | D164: Daily | E164: 每日
B165: PEROID_TYPE_SEASON | C165: 시즌 | D165: Seasonal | E165: 限期
B166: PEROID_TYPE_WEEKLY | C166: 주간 | D166: Weekly | E166: 每周
B167: POPUP_HERO_INFO_AUTO_CLOSE | C167: {0}초 후 닫힘. 터치하면 취소됩니다. | D167: Closes in {0}s. Tap to cancel. | E167: {0}秒后关闭。点击即可取消。
B168: POPUP_REGION_CHARACTERS | C168: 대표 장수 | D168: Signature Officers | E168: 代表武将
B169: POPUP_REGION_SELECT_INFO | C169: 군주를 선택해 주세요. | D169: Please choose your lord. | E169: 请选择君主。
B170: REGION_NAME_ETC | C170: 군 | D170: Etc | E170: 群
B171: REGION_NAME_FULL_ETC | C171: 군웅 | D171: Etc | E171: 群雄
B172: REGION_NAME_FULL_SHU | C172: 촉나라 | D172: Shu | E172: 蜀国
B173: REGION_NAME_FULL_WEI | C173: 위나라 | D173: Wei | E173: 魏国
... B178: SCREEN_DD_TITLE | C178: 고대 무장전 | D178: Ancient Officers | E178: 古代武将战
A179: CLASS | B179: ="SORTTYPE_"&A179 -> SORTTYPE_CLASS | C179: 역할 | D179: Class | E179: 职业
A180: GRADE | B180: ="SORTTYPE_"&A180 -> SORTTYPE_GRADE | C180: 등급 | D180: Grade | E180: 品阶
A181: LEVEL | B181: ="SORTTYPE_"&A181 -> SORTTYPE_LEVEL | C181: 레벨 | D181: Level | E181: 等级
A182: POWER | B182: ="SORTTYPE_"&A182 -> SORTTYPE_POWER | C182: 전투력 | D182: Combat Power | E182: 战斗力
A183: REGION | B183: ="SORTTYPE_"&A183 -> SORTTYPE_REGION | C183: 국가 | D183: Nation | E183: 国家
B184: SUMMON_DESC_REWARD_INFO | C184: 영혼석 10개 획득 100% | D184: 10 Soul Stones, 100% guaranteed | E184: 100%获得10个魂石
B185: SUMMON_HOST | C185: 주최자 | D185: Host | E185: 主办者
B186: SUMMON_REMAIN_TIME_HOST_CHANGE | C186: 주최자 변경까지 남은시간 | D186: Time Until Host Change | E186: 主办者更换倒计时
B187: SUMMON_TICKET_COUNT | C187: 연회권 {0}장 | D187: {0} Banquet Tickets | E187: 宴会券{0}张
B188: SUMMON_TITLE | C188: 연회 | D188: Banquet | E188: 宴会
B189: SUMMON_TYPE_ALL | C189: 전체 장수 | D189: All Officers | E189: 全部武将
B190: SUMMON_TYPE_COUNTRY | C190: {0} 확률 증가 | D190: {0} Rate Up | E190: {0}概率提升
B191: TAB_ALL | C191: 전체 | D191: All | E191: 全部
B192: UI_ACTIVATE | C192: 활성화 | D192: Enabled | E192: 启用
B193: UI_AFK_TITLE | C193: 방치보상 | D193: Idle Rewards | E193: 挂机奖励
B194: UI_AFK_TITLE_S | C194: 방치보상 | D194: IDLE RWD | E194: 挂机奖励
B195: UI_BANNER_STORY | C195: 스토리 | D195: Story | E195: 剧情
... B216: UI_FILTER | C216: 필터 | D216: Filter | E216: 筛选
A217: class | B217: ="UI_FILTER_"&UPPER(A217) -> UI_FILTER_CLASS | C217: 역할 | D217: Class | E217: 职业
A218: grade | B218: ="UI_FILTER_"&UPPER(A218) -> UI_FILTER_GRADE | C218: 등급 | D218: Grade | E218: 品阶
A219: region | B219: ="UI_FILTER_"&UPPER(A219) -> UI_FILTER_REGION | C219: 국가 | D219: Nation | E219: 国家
A220: sort | B220: ="UI_FILTER_"&UPPER(A220) -> UI_FILTER_SORT | C220: 정렬 | D220: Sort | E220: 排序
B221: UI_FINISH_CONFIRM | C221: 마무리 | D221: Finish | E221: 收尾
B222: UI_FRIENDSHIP | C222: 인연 | D222: Bonds | E222: 羁绊
B223: UI_GRADE | C223: 등급 | D223: GRADE | E223: 品阶
B224: UI_JOIN | C224: 참가 | D224: Join | E224: 参加
...

Sheet String_Item
A1: # | B1: key | C1: kr | D1: en | E1: cn
A2: string | B2: string | C2: string | D2: string | E2: string
A3: none | B3: ="CATEGORY_"&UPPER(A3) -> CATEGORY_NONE | C3: 전체 | D3: All | E3: 全部
A4: Currency | B4: ="CATEGORY_"&UPPER(A4) -> CATEGORY_CURRENCY | C4: 재화 | D4: Currency | E4: 货币
A5: Soul_Stone | B5: ="CATEGORY_"&UPPER(A5) -> CATEGORY_SOUL_STONE | C5: 영혼석 | D5: Soul Stone | E5: 魂石
A6: Bundle | B6: ="CATEGORY_"&UPPER(A6) -> CATEGORY_BUNDLE | C6: 번들 | D6: Bundle | E6: 礼包
A7: Item | B7: ="CATEGORY_"&UPPER(A7) -> CATEGORY_ITEM | C7: 아이템 | D7: Item | E7: 道具
A8: TreasurePiece | B8: ="CATEGORY_"&UPPER(A8) -> CATEGORY_TREASUREPIECE | C8: 보물 파편 | D8: Treasure Shard | E8: 宝物碎片
A9: TICKET_GACHA | B9: ="CATEGORY_"&UPPER(A9) -> CATEGORY_TICKET_GACHA | C9: 연회권 | D9: Banquet Ticket | E9: 宴会券
A10: Treasure | B10: ="CATEGORY_"&UPPER(A10) -> CATEGORY_TREASURE | C10: 보물 | D10: Treasure | E10: 宝物
A11: ContentsTicket | B11: ="CATEGORY_"&UPPER(A11) -> CATEGORY_CONTENTSTICKET | C11: 입장권 | D11: Entry Ticket | E11: 入场券
A12: MAX | B12: ="CATEGORY_"&UPPER(A12) -> CATEGORY_MAX | C12: 기타 | D12: Other | E12: 其他
A13: Soul_Stone | B13: ="NAME_"&UPPER(A13) -> NAME_SOUL_STONE | C13: [{0}] 영혼석 | D13: [{0}] Soul Stone | E13: [{0}]魂石
A14: Rice | B14: ="NAME_"&UPPER(A14) -> NAME_RICE | C14: 군량 | D14: Provisions | E14: 军粮
A15: Gold | B15: ="NAME_"&UPPER(A15) -> NAME_GOLD | C15: 금화 | D15: Gold | E15: 金币
A16: goldfree | B16: ="NAME_"&UPPER(A16) -> NAME_GOLDFREE | C16: 금화 | D16: Gold | E16: 金币
A17: goldpaid | B17: ="NAME_"&UPPER(A17) -> NAME_GOLDPAID | C17: RP | D17: RP | E17: RP
A18: TimeStone | B18: ="NAME_"&UPPER(A18) -> NAME_TIMESTONE | C18: 시간석 | D18: Time Stone | E18: 时之石
A19: PocketRice | B19: ="NAME_"&UPPER(A19) -> NAME_POCKETRICE | C19: 군량 주머니
A20: PocketGold | B20: ="NAME_"&UPPER(A20) -> NAME_POCKETGOLD | C20: 금화 주머니
A21: PocketTimeStone | B21: ="NAME_"&UPPER(A21) -> NAME_POCKETTIMESTONE | C21: 시간석 주머니
A22: RandomBoxSoulStoneClass | B22: ="NAME_"&UPPER(A22) -> NAME_RANDOMBOXSOULSTONECLASS | C22: 클래스 영혼석 랜덤박스
A23: RandomBoxSoulStoneDedicated | B23: ="NAME_"&UPPER(A23) -> NAME_RANDOMBOXSOULSTONEDEDICATED | C23: 전용 영혼석 랜덤박스
A24: RandomBoxTreasurePiece | B24: ="NAME_"&UPPER(A24) -> NAME_RANDOMBOXTREASUREPIECE | C24: 보물 조각 랜덤박스
A25: TicketGachaNormal | B25: ="NAME_"&UPPER(A25) -> NAME_TICKETGACHANORMAL | C25: 일반 연회권
A26: TicketGachaPremium | B26: ="NAME_"&UPPER(A26) -> NAME_TICKETGACHAPREMIUM | C26: 고급 연회권
A27: PointRaid | B27: ="NAME_"&UPPER(A27) -> NAME_POINTRAID | C27: 레이드 포인트
A28: PointTournament | B28: ="NAME_"&UPPER(A28) -> NAME_POINTTOURNAMENT | C28: 토너먼트 포인트
A29: SoulStonePublic | B29: ="NAME_"&UPPER(A29) -> NAME_SOULSTONEPUBLIC | C29: 공용 영혼석
A30: SoulStoneDedicated | B30: ="NAME_"&UPPER(A30) -> NAME_SOULSTONEDEDICATED | C30: 전용 영혼석
... A36: Pass | B36: ="NAME_"&UPPER(A36) -> NAME_PASS | C36: 출사표
A37: Rice | B37: ="DESC_"&UPPER(A37) -> DESC_RICE
A38: Gold | B38: ="DESC_"&UPPER(A38) -> DESC_GOLD
A39: gold_free | B39: ="DESC_"&UPPER(A39) -> DESC_GOLD_FREE
A40: gold_paid | B40: ="DESC_"&UPPER(A40) -> DESC_GOLD_PAID
A41: TimeStone | B41: ="DESC_"&UPPER(A41) -> DESC_TIMESTONE
A42: PocketRice | B42: ="DESC_"&UPPER(A42) -> DESC_POCKETRICE
A43: PocketGold | B43: ="DESC_"&UPPER(A43) -> DESC_POCKETGOLD
A44: PocketTimeStone | B44: ="DESC_"&UPPER(A44) -> DESC_POCKETTIMESTONE
A45: RandomBoxSoulStoneClass | B45: ="DESC_"&UPPER(A45) -> DESC_RANDOMBOXSOULSTONECLASS
A46: RandomBoxSoulStoneDedicated | B46: ="DESC_"&UPPER(A46) -> DESC_RANDOMBOXSOULSTONEDEDICATED
A47: RandomBoxTreasurePiece | B47: ="DESC_"&UPPER(A47) -> DESC_RANDOMBOXTREASUREPIECE
A48: TicketGachaNormal | B48: ="DESC_"&UPPER(A48) -> DESC_TICKETGACHANORMAL
... A59: Pass | B59: ="DESC_"&UPPER(A59) -> DESC_PASS

Sheet String_Shop
A1: # | B1: key | C1: kr | D1: en | E1: cn
A2: string | B2: string | C2: string | D2: string | E2: string
A3: goldfree | B3: ="CATEGORY_"&UPPER(A3) -> CATEGORY_GOLDFREE | C3: 금화
A4: goldpaid | B4: ="CATEGORY_"&UPPER(A4) -> CATEGORY_GOLDPAID | C4: RP 충전하기
A5: rice | B5: ="CATEGORY_"&UPPER(A5) -> CATEGORY_RICE | C5: 군량
A6: package | B6: ="CATEGORY_"&UPPER(A6) -> CATEGORY_PACKAGE | C6: 패키지
A7: pass | B7: ="CATEGORY_"&UPPER(A7) -> CATEGORY_PASS | C7: 출사표
A8: gold_paid_1000 | B8: ="NAME_"&UPPER(A8) -> NAME_GOLD_PAID_1000 | C8: RP 1000개
A9: gold_paid_3000 | B9: ="NAME_"&UPPER(A9) -> NAME_GOLD_PAID_3000 | C9: RP 3000개
A10: gold_paid_5000 | B10: ="NAME_"&UPPER(A10) -> NAME_GOLD_PAID_5000 | C10: RP 5000개
A11: gold_paid_7000 | B11: ="NAME_"&UPPER(A11) -> NAME_GOLD_PAID_7000 | C11: RP 7000개
A12: gold_paid_10000 | B12: ="NAME_"&UPPER(A12) -> NAME_GOLD_PAID_10000 | C12: RP 10000개
A13: gold_paid_30000 | B13: ="NAME_"&UPPER(A13) -> NAME_GOLD_PAID_30000 | C13: RP 30000개
A14: gold_paid_50000 | B14: ="NAME_"&UPPER(A14) -> NAME_GOLD_PAID_50000 | C14: RP 50000개
A15: gold_paid_70000 | B15: ="NAME_"&UPPER(A15) -> NAME_GOLD_PAID_70000 | C15: RP 70000개
A16: gold_free_1000 | B16: ="NAME_"&UPPER(A16) -> NAME_GOLD_FREE_1000 | C16: 금화 1000개
A17: gold_free_3000 | B17: ="NAME_"&UPPER(A17) -> NAME_GOLD_FREE_3000 | C17: 금화 3000개
A18: gold_free_5000 | B18: ="NAME_"&UPPER(A18) -> NAME_GOLD_FREE_5000 | C18: 금화 5000개
A19: gold_free_7000 | B19: ="NAME_"&UPPER(A19) -> NAME_GOLD_FREE_7000 | C19: 금화 7000개
... A34: battle_pass_season_1 | B34: ="NAME_"&UPPER(A34) -> NAME_BATTLE_PASS_SEASON_1 | C34: 출사표 시즌1
A35: gold_paid_1000 | B35: ="DESC_"&UPPER(A35) -> DESC_GOLD_PAID_1000
A36: gold_paid_3000 | B36: ="DESC_"&UPPER(A36) -> DESC_GOLD_PAID_3000
A37: gold_paid_5000 | B37: ="DESC_"&UPPER(A37) -> DESC_GOLD_PAID_5000
A38: gold_paid_7000 | B38: ="DESC_"&UPPER(A38) -> DESC_GOLD_PAID_7000
A39: gold_paid_10000 | B39: ="DESC_"&UPPER(A39) -> DESC_GOLD_PAID_10000
A40: gold_paid_30000 | B40: ="DESC_"&UPPER(A40) -> DESC_GOLD_PAID_30000
A41: gold_paid_50000 | B41: ="DESC_"&UPPER(A41) -> DESC_GOLD_PAID_50000
A42: gold_paid_70000 | B42: ="DESC_"&UPPER(A42) -> DESC_GOLD_PAID_70000
A43: gold_free_1000 | B43: ="DESC_"&UPPER(A43) -> DESC_GOLD_FREE_1000
A44: gold_free_3000 | B44: ="DESC_"&UPPER(A44) -> DESC_GOLD_FREE_3000
A45: gold_free_5000 | B45: ="DESC_"&UPPER(A45) -> DESC_GOLD_FREE_5000
A46: gold_free_7000 | B46: ="DESC_"&UPPER(A46) -> DESC_GOLD_FREE_7000
... A61: battle_pass_season_1 | B61: ="DESC_"&UPPER(A61) -> DESC_BATTLE_PASS_SEASON_1
B62: UI_BATTLE_PASS_1_REWARD_TITLE | C62: 출사표 완료보상!!
B63: UI_BATTLE_PASS_1_REWARD_SUB | C63: 재화 획득!!
B64: UI_BATTLE_PASS_1_REWARD_DESC | C64: 광고 제거\n특사 임무 가능

Sheet String_Mission
A1: #Mission Key | B1: key | C1: kr | D1: en | E1: cn
A2: string | B2: string | C2: string | D2: string | E2: string
A3: military_training | B3: =UPPER(A3)&"_TITLE" -> MILITARY_TRAINING_TITLE | C3: 군사 훈련 지휘 | D3: Command Military Training | E3: 指挥军事训练
A4: rally_remnants | B4: =UPPER(A4)&"_TITLE" -> RALLY_REMNANTS_TITLE | C4: 패잔병 수습 | D4: Rally the Remnants | E4: 收拢残兵
A5: bandit_subjugation | B5: =UPPER(A5)&"_TITLE" -> BANDIT_SUBJUGATION_TITLE | C5: 산적 토벌 | D5: Subjugate Bandits | E5: 讨伐山贼
A6: border_defense | B6: =UPPER(A6)&"_TITLE" -> BORDER_DEFENSE_TITLE | C6: 변경 수비 | D6: Defend the Frontier | E6: 镇守边境
A7: tax_reform | B7: =UPPER(A7)&"_TITLE" -> TAX_REFORM_TITLE | C7: 조세 제도 정비 | D7: Reform the Tax System | E7: 整顿税制
A8: foreign_diplomacy | B8: =UPPER(A8)&"_TITLE" -> FOREIGN_DIPLOMACY_TITLE | C8: 인근 제후국 외교 | D8: Diplomacy with Neighboring Lords | E8: 邻近诸侯外交
A9: enemy_intelligence | B9: =UPPER(A9)&"_TITLE" -> ENEMY_INTELLIGENCE_TITLE | C9: 적진 첩보 수집 | D9: Gather Enemy Intelligence | E9: 收集敌营情报
A10: tactics_research | B10: =UPPER(A10)&"_TITLE" -> TACTICS_RESEARCH_TITLE | C10: 병법서 연구 | D10: Study the Art of War | E10: 研读兵书
A11: refugee_persuasion | B11: =UPPER(A11)&"_TITLE" -> REFUGEE_PERSUASION_TITLE | C11: 유랑민 귀순 설득 | D11: Persuade Refugees to Submit | E11: 劝降流民归顺
A12: recruit_talent | B12: =UPPER(A12)&"_TITLE" -> RECRUIT_TALENT_TITLE | C12: 재야 인재 영입 | D12: Recruit Hidden Talent | E12: 招揽在野人才

Sheet String_Hero
A1: #type | B1: #key | C1: #region | D1: key | E1: kr | F1: en | G1: cn
A2: string | B2: string | C2: string | D2: string | E2: string | F2: string | G2: string
D3: CLASSTYPE_ARCHER | E3: 궁장 | F3: Archer | G3: 弓将
D4: CLASSTYPE_CHAMPION | E4: 용장 | F4: Champion | G4: 勇将
D5: CLASSTYPE_CHASER | E5: 추격자 | F5: Chaser | G5: 追击者
D6: CLASSTYPE_COMMANDER | E6: 지휘관 | F6: Commander | G6: 指挥官
D7: CLASSTYPE_STRATEGIST | E7: 책사 | F7: Strategist | G7: 谋士
D8: CLASSTYPE_VANGUARD | E8: 선봉장 | F8: Vanguard | G8: 先锋将
A9: COURTESY | B9: LuBu | C9: etc | D9: =UPPER(A9)&"_"&UPPER(C9)&"_"&UPPER(B9) -> COURTESY_ETC_LUBU | E9: 봉선 | F9: Fengxian | G9: 奉先
A10: COURTESY | B10: GuanYu | C10: shu | D10: =UPPER(A10)&"_"&UPPER(C10)&"_"&UPPER(B10) -> COURTESY_SHU_GUANYU | E10: 운장 | F10: Yunchang | G10: 云长
A11: COURTESY | B11: HuangZhong | C11: shu | D11: =UPPER(A11)&"_"&UPPER(C11)&"_"&UPPER(B11) -> COURTESY_SHU_HUANGZHONG | E11: 항승 | F11: Hansheng | G11: 汉升
A12: COURTESY | B12: LiuBei | C12: shu | D12: =UPPER(A12)&"_"&UPPER(C12)&"_"&UPPER(B12) -> COURTESY_SHU_LIUBEI | E12: 현덕 | F12: Xuande | G12: 玄德
A13: COURTESY | B13: ZhangFei | C13: shu | D13: =UPPER(A13)&"_"&UPPER(C13)&"_"&UPPER(B13) -> COURTESY_SHU_ZHANGFEI | E13: 익덕 | F13: Yide | G13: 益德
A14: COURTESY | B14: ZhaoYun | C14: shu | D14: =UPPER(A14)&"_"&UPPER(C14)&"_"&UPPER(B14) -> COURTESY_SHU_ZHAOYUN | E14: 자룡 | F14: Zilong | G14: 子龙
A15: COURTESY | B15: ZhugeLiang | C15: shu | D15: =UPPER(A15)&"_"&UPPER(C15)&"_"&UPPER(B15) -> COURTESY_SHU_ZHUGELIANG | E15: 공명 | F15: Kongming | G15: 孔明
A16: COURTESY | B16: CaoCao | C16: wei | D16: =UPPER(A16)&"_"&UPPER(C16)&"_"&UPPER(B16) -> COURTESY_WEI_CAOCAO | E16: 맹덕 | F16: Mengde | G16: 孟德
A17: COURTESY | B17: CaoRen | C17: wei | D17: =UPPER(A17)&"_"&UPPER(C17)&"_"&UPPER(B17) -> COURTESY_WEI_CAOREN | E17: 자효 | F17: Zixiao | G17: 子孝
A18: COURTESY | B18: XiahouDun | C18: wei | D18: =UPPER(A18)&"_"&UPPER(C18)&"_"&UPPER(B18) -> COURTESY_WEI_XIAHOUDUN | E18: 원양 | F18: Yuanrang | G18: 元让
A19: COURTESY | B19: XiahouYuan | C19: wei | D19: =UPPER(A19)&"_"&UPPER(C19)&"_"&UPPER(B19) -> COURTESY_WEI_XIAHOUYUAN | E19: 묘재 | F19: Miaocai | G19: 妙才
A20: COURTESY | B20: XunYu | C20: wei | D20: =UPPER(A20)&"_"&UPPER(C20)&"_"&UPPER(B20) -> COURTESY_WEI_XUNYU | E20: 문약 | F20: Wenruo | G20: 文若
... A48: DESC_TALK | B48: ZhouYu | C48: wu | D48: =UPPER(A48)&"_"&UPPER(C48)&"_"&UPPER(B48) -> DESC_TALK_WU_ZHOUYU | E48: "불의 연주가 시작되었다. 잔을 들어라." | F48: "The music of fire has begun. Raise your cup." | G48: “火的乐章已经奏响。 举杯吧。”
D49: HISTORICAL_NAME_JIANGSHANG | E49: 강상 | F49: Jiang Shang | G49: 姜尚
D50: HISTORICAL_NAME_JIANGSHANG_DESC | E50: 낚시꾼의 시조 | F50: Father of Anglers | G50: 垂钓者之祖
D51: HISTORICAL_NAME_LIANPO | E51: 염파 | F51: Lian Po | G51: 廉颇
D52: HISTORICAL_NAME_LIANPO_DESC | E52: 백전백승의 노익장 | F52: Undefeated Old Warhorse | G52: 百战百胜的老将
D53: HISTORICAL_NAME_QINSHIHUANG | E53: 진시황 | F53: Qin Shi Huang | G53: 秦始皇
D54: HISTORICAL_NAME_QINSHIHUANG_DESC | E54: 최초의 황제 | F54: The First Emperor | G54: 最初的皇帝
D55: HISTORICAL_NAME_XIANGYU | E55: 항우 | F55: Xiang Yu | G55: 项羽
D56: HISTORICAL_NAME_XIANGYU_DESC | E56: 최강의 역발산 패왕 | F56: Mountain-Lifting Overlord | G56: 力拔山河的最强霸王
D57: HISTORICAL_NAME_YANGYOUJI | E57: 양유기 | F57: Yang Youji | G57: 养由基
D58: HISTORICAL_NAME_YANGYOUJI_DESC | E58: 백발백중의 신궁 | F58: Divine Archer Who Never Misses | G58: 百发百中的神射手
D59: HISTORICAL_NAME_YUEYI | E59: 악의 | F59: Yue Yi | G59: 乐毅
D60: HISTORICAL_NAME_YUEYI_DESC | E60: 연나라의 구국명장 | F60: Savior General of Yan | G60: 燕国的救国名将
A61: NAME | B61: LuBu | C61: etc | D61: =UPPER(A61)&"_"&UPPER(C61)&"_"&UPPER(B61) -> NAME_ETC_LUBU | E61: 여포 | F61: Lu Bu | G61: 吕布
A62: NAME | B62: GuanYu | C62: shu | D62: =UPPER(A62)&"_"&UPPER(C62)&"_"&UPPER(B62) -> NAME_SHU_GUANYU | E62: 관우 | F62: Guan Yu | G62: 关羽
A63: NAME | B63: HuangZhong | C63: shu | D63: =UPPER(A63)&"_"&UPPER(C63)&"_"&UPPER(B63) -> NAME_SHU_HUANGZHONG | E63: 황충 | F63: Huang Zhong | G63: 黄忠
A64: NAME | B64: LiuBei | C64: shu | D64: =UPPER(A64)&"_"&UPPER(C64)&"_"&UPPER(B64) -> NAME_SHU_LIUBEI | E64: 유비 | F64: Liu Bei | G64: 刘备
A65: NAME | B65: ZhangFei | C65: shu | D65: =UPPER(A65)&"_"&UPPER(C65)&"_"&UPPER(B65) -> NAME_SHU_ZHANGFEI | E65: 장비 | F65: Zhang Fei | G65: 张飞
A66: NAME | B66: ZhaoYun | C66: shu | D66: =UPPER(A66)&"_"&UPPER(C66)&"_"&UPPER(B66) -> NAME_SHU_ZHAOYUN | E66: 조운 | F66: Zhao Yun | G66: 赵云
A67: NAME | B67: ZhugeLiang | C67: shu | D67: =UPPER(A67)&"_"&UPPER(C67)&"_"&UPPER(B67) -> NAME_SHU_ZHUGELIANG | E67: 제갈량 | F67: Zhuge Liang | G67: 诸葛亮
A68: NAME | B68: CaoCao | C68: wei | D68: =UPPER(A68)&"_"&UPPER(C68)&"_"&UPPER(B68) -> NAME_WEI_CAOCAO | E68: 조조 | F68: Cao Cao | G68: 曹操
A69: NAME | B69: CaoRen | C69: wei | D69: =UPPER(A69)&"_"&UPPER(C69)&"_"&UPPER(B69) -> NAME_WEI_CAOREN | E69: 조인 | F69: Cao Ren | G69: 曹仁
A70: NAME | B70: XiahouDun | C70: wei | D70: =UPPER(A70)&"_"&UPPER(C70)&"_"&UPPER(B70) -> NAME_WEI_XIAHOUDUN | E70: 하후돈 | F70: Xiahou Dun | G70: 夏侯惇
A71: NAME | B71: XiahouYuan | C71: wei | D71: =UPPER(A71)&"_"&UPPER(C71)&"_"&UPPER(B71) -> NAME_WEI_XIAHOUYUAN | E71: 하후연 | F71: Xiahou Yuan | G71: 夏侯渊
A72: NAME | B72: XunYu | C72: wei | D72: =UPPER(A72)&"_"&UPPER(C72)&"_"&UPPER(B72) -> NAME_WEI_XUNYU | E72: 순욱 | F72: Xun Yu | G72: 荀彧
... A80: NAME | B80: ZhouYu | C80: wu | D80: =UPPER(A80)&"_"&UPPER(C80)&"_"&UPPER(B80) -> NAME_WU_ZHOUYU | E80: 주유 | F80: Zhou Yu | G80: 周瑜
D81: REGION_MASTER_DESC_SHU | E81: 고결한 이상주의자 | F81: The Noble Idealist | G81: 高洁的理想主义者
D82: REGION_MASTER_DESC_SUB_SHU | E82: 인의와 명분으로 민심을 결속시키고 대업을 꿈꾸는 왕도 | F82: The kingly way: binding the people's hearts with virtue and just cause, dreaming of a great destiny | G82: 以仁义与名分凝聚民心、胸怀大业的王道
D83: REGION_MASTER_DESC_SUB_WEI | E83: 천하의 인재를 거느리며 판도를 흔드는 패도 | F83: The conqueror's way: commanding the realm's finest talent and shaking the balance of power | G83: 统御天下英才、搅动天下格局的霸道
D84: REGION_MASTER_DESC_SUB_WU | E84: 지형과 인재의 화합으로 세운 철벽의 수성 | F84: An iron wall raised from terrain and talent in harmony | G84: 凭地利与人和筑成的铁壁守势
D85: REGION_MASTER_DESC_WEI | E85: 난세의 간웅 | F85: The Cunning Hero of Chaos | G85: 乱世奸雄
D86: REGION_MASTER_DESC_WU | E86: 실용적인 수호자 | F86: The Pragmatic Guardian | G86: 务实的守护者
A87: NAME | B87: YuanShao | C87: etc | D87: =UPPER(A87)&"_"&UPPER(C87)&"_"&UPPER(B87) -> NAME_ETC_YUANSHAO | E87: 원소 | F87: Yuan Shao | G87: 袁绍
A88: NAME | B88: YanLiang | C88: etc | D88: =UPPER(A88)&"_"&UPPER(C88)&"_"&UPPER(B88) -> NAME_ETC_YANLIANG | E88: 안량 | F88: Yan Liang | G88: 颜良
A89: NAME | B89: WenChou | C89: etc | D89: =UPPER(A89)&"_"&UPPER(C89)&"_"&UPPER(B89) -> NAME_ETC_WENCHOU | E89: 문추 | F89: Wen Chou | G89: 文丑
A90: NAME | B90: SongXian | C90: etc | D90: =UPPER(A90)&"_"&UPPER(C90)&"_"&UPPER(B90) -> NAME_ETC_SONGXIAN | E90: 송헌 | F90: Song Xian | G90: 宋宪
A91: NAME | B91: WeiXU | C91: etc | D91: =UPPER(A91)&"_"&UPPER(C91)&"_"&UPPER(B91) -> NAME_ETC_WEIXU | E91: 위속 | F91: Wei Xu | G91: 魏续
A92: NAME | B92: XuHuang | C92: wei | D92: =UPPER(A92)&"_"&UPPER(C92)&"_"&UPPER(B92) -> NAME_WEI_XUHUANG | E92: 서황 | F92: Xu Huang | G92: 徐晃
A93: NAME | B93: FanJiang | C93: wei | D93: =UPPER(A93)&"_"&UPPER(C93)&"_"&UPPER(B93) -> NAME_WEI_FANJIANG | E93: 범강 | F93: Fan Jiang | G93: 范疆
A94: NAME | B94: ZhangDa | C94: wei | D94: =UPPER(A94)&"_"&UPPER(C94)&"_"&UPPER(B94) -> NAME_WEI_ZHANGDA | E94: 장달 | F94: Zhang Da | G94: 张达
A95: COURTESY | B95: YuanShao | C95: etc | D95: =UPPER(A95)&"_"&UPPER(C95)&"_"&UPPER(B95) -> COURTESY_ETC_YUANSHAO | E95: 본초 | F95: Benchu | G95: 本初
A96: COURTESY | B96: YanLiang | C96: etc | D96: =UPPER(A96)&"_"&UPPER(C96)&"_"&UPPER(B96) -> COURTESY_ETC_YANLIANG | E96: - | F96: - | G96: -
A97: COURTESY | B97: WenChou | C97: etc | D97: =UPPER(A97)&"_"&UPPER(C97)&"_"&UPPER(B97) -> COURTESY_ETC_WENCHOU | E97: - | F97: - | G97: -
A98: COURTESY | B98: XuHuang | C98: wei | D98: =UPPER(A98)&"_"&UPPER(C98)&"_"&UPPER(B98) -> COURTESY_WEI_XUHUANG | E98: 공명 | F98: Gongming | G98: 公明
... A102: DESC_TALK | B102: XuHuang | C102: wei | D102: =UPPER(A102)&"_"&UPPER(C102)&"_"&UPPER(B102) -> DESC_TALK_WEI_XUHUANG | E102: "내 도끼에 자비란 없다. 각오를 단단히 해야 할 것이야!" | F102: "My axe knows no mercy. You had best brace yourself!" | G102: “我的斧下没有慈悲。 你可要做好准备！”
A103: SKILL | B103: LiuBei | C103: title | D103: =A103&"_"&UPPER(B103)&"_"&UPPER(C103) -> SKILL_LIUBEI_TITLE | E103: 의용장 | F103: Righteous Valor | G103: 义勇将
A104: SKILL | B104: LiuBei | C104: desc | D104: =A104&"_"&UPPER(B104)&"_"&UPPER(C104) -> SKILL_LIUBEI_DESC | E104: 아군의 이동속도가 증가하고, 5초간 최대 체력의 50%를 회복한다. | F104: Increases allies' move speed and restores 50% of max health over 5 seconds. | G104: 提升友军移动速度，并在5秒内恢复最大生命值的50%。

Sheet String_Treasure
A1: #Treasure_key | B1: key | C1: kr | D1: en | E1: cn
A2: string | B2: string | C2: string | D2: string | E2: string
A3: liutao | B3: ="NAME_" & UPPER(A3) -> NAME_LIUTAO | C3: 육도 | D3: Six Secret Teachings | E3: 六韬
A4: sanlue | B4: ="NAME_" & UPPER(A4) -> NAME_SANLUE | C4: 삼략 | D4: Three Strategies | E4: 三略
A5: weiliaozi | B5: ="NAME_" & UPPER(A5) -> NAME_WEILIAOZI | C5: 위료자 | D5: Wei Liaozi | E5: 尉缭子
A6: commanders_banner | B6: ="NAME_" & UPPER(A6) -> NAME_COMMANDERS_BANNER | C6: 장수기 | D6: Banner of Command | E6: 将旗
A7: tiger_tally | B7: ="NAME_" & UPPER(A7) -> NAME_TIGER_TALLY | C7: 호부 | D7: Tiger Tally | E7: 虎符
A8: war_drum_gong | B8: ="NAME_" & UPPER(A8) -> NAME_WAR_DRUM_GONG | C8: 금고 | D8: War Drum and Gong | E8: 金鼓
A9: sima_fa | B9: ="NAME_" & UPPER(A9) -> NAME_SIMA_FA | C9: 사마법 | D9: Methods of the Sima | E9: 司马法
A10: wuzi | B10: ="NAME_" & UPPER(A10) -> NAME_WUZI | C10: 오자 | D10: Wuzi | E10: 吴子
A11: red_cliff_flame | B11: ="NAME_" & UPPER(A11) -> NAME_RED_CLIFF_FLAME | C11: 적벽의 화염 | D11: Flames of Red Cliff | E11: 赤壁之焰
A12: bangcheonhwagug_shard | B12: ="NAME_" & UPPER(A12) -> NAME_BANGCHEONHWAGUG_SHARD | C12: 방천화극 파편 | D12: Fangtian Halberd Shard | E12: 方天画戟碎片
A13: ganjiang_moye | B13: ="NAME_" & UPPER(A13) -> NAME_GANJIANG_MOYE | C13: 간장막야 | D13: Ganjiang and Moye | E13: 干将莫邪
A14: chungou | B14: ="NAME_" & UPPER(A14) -> NAME_CHUNGOU | C14: 순구 | D14: Chungou | E14: 纯钩
... A47: map_of_queen_mother_of_the_west | B47: ="NAME_" & UPPER(A47) -> NAME_MAP_OF_QUEEN_MOTHER_OF_THE_WEST | C47: 서왕모도 | D47: Portrait of the Queen Mother of the West | E47: 西王母图

Sheet String_ScenarioTalk
A1: #key | B1: #idx | C1: key | D1: #PC | E1: Target | F1: #name | G1: kr | H1: en | I1: cn
A2: string | B2: int | C2: string | D2: string | E2: string | F2: string | G2: string | H2: string | I2: string
A3: NODE_2 | B3: 0 | C3: =CONCATENATE(A3, "_", B3, IF(D3<>"", "_"&D3, "")) -> NODE_2_0 | E3: =VLOOKUP(F3,Overview!$A$1:$B$28,2,FALSE) -> CaoRen | F3: 조인 | G3: 흥! 아직도 도적 떼가 설치다니!! | H3: Hah! Bandit rabble, still crawling about!! | I3: 哼！贼寇竟还敢猖狂！！
A4: =A3 -> NODE_2 | B4: =B3+1 -> 1 | C4: =CONCATENATE(A4, "_", B4, IF(D4<>"", "_"&D4, "")) -> NODE_2_1 | E4: =VLOOKUP(F4,Overview!$A$1:$B$28,2,FALSE) -> CaoRen | F4: 조인 | G4: 죽여주마!! | H4: I'll cut you down!! | I4: 我这就宰了你们！！
A5: =A4 -> NODE_2 | B5: =B4+1 -> 2 | C5: =CONCATENATE(A5, "_", B5, IF(D5<>"", "_"&D5, "")) -> NODE_2_2
A6: =A5 -> NODE_2 | B6: =B5+1 -> 3 | C6: =CONCATENATE(A6, "_", B6, IF(D6<>"", "_"&D6, "")) -> NODE_2_3 | E6: =VLOOKUP(F6,Overview!$A$1:$B$28,2,FALSE) -> CaoRen | F6: 조인 | G6: 흥! 별것도 아닌 것들이.. | H6: Hah! Nothing to them at all.. | I6: 哼！不过是些无名之辈……
A7: =A6 -> NODE_2 | B7: =B6+1 -> 4 | C7: =CONCATENATE(A7, "_", B7, IF(D7<>"", "_"&D7, "")) -> NODE_2_4 | E7: Etc | G7: 대장!! 조조님이 드디어 거병하셨답니다! | H7: Chief!! Lord Cao Cao has finally raised his army! | I7: 将军！！ 曹操大人终于起兵了！
A8: =A7 -> NODE_2 | B8: =B7+1 -> 5 | C8: =CONCATENATE(A8, "_", B8, IF(D8<>"", "_"&D8, "")) -> NODE_2_5 | E8: =VLOOKUP(F8,Overview!$A$1:$B$28,2,FALSE) -> CaoRen | F8: 조인 | G8: 맹덕 형님이?? | H8: Brother Mengde has?? | I8: 孟德兄他？？
A9: =A8 -> NODE_2 | B9: =B8+1 -> 6 | C9: =CONCATENATE(A9, "_", B9, IF(D9<>"", "_"&D9, "")) -> NODE_2_6 | E9: =VLOOKUP(F9,Overview!$A$1:$B$28,2,FALSE) -> CaoRen | F9: 조인 | G9: 좋다!! 우리도 가서 힘을 보태자. 너희들도 나를 따라오너라! | H9: Good!! We ride to lend our strength. All of you, follow me! | I9: 好！！我们也去助他一臂之力。 你们都跟我来！
A10: =A9 -> NODE_2 | B10: =B9+1 -> 7 | C10: =CONCATENATE(A10, "_", B10, IF(D10<>"", "_"&D10, "")) -> NODE_2_7
A11: =A10 -> NODE_2 | B11: =B10+1 -> 8 | C11: =CONCATENATE(A11, "_", B11, IF(D11<>"", "_"&D11, "")) -> NODE_2_8 | E11: =VLOOKUP(F11,Overview!$A$1:$B$28,2,FALSE) -> CaoCao | F11: 조조 | G11: 이 난세를 헤쳐 나가려면 힘을 키워야 한다. | H11: To cut a path through this broken age, we must build up our strength. | I11: 要在这乱世中杀出一条路， 就得积蓄力量。
A12: =A11 -> NODE_2 | B12: =B11+1 -> 9 | C12: =CONCATENATE(A12, "_", B12, IF(D12<>"", "_"&D12, "")) -> NODE_2_9 | E12: =VLOOKUP(F12,Overview!$A$1:$B$28,2,FALSE) -> XiahouDun | F12: 하후돈 | G12: 걱정마라 아만! 내가 있는데 뭐가 걱정인게야 캬캬캬! | H12: Don't you worry, Aman! With me around, what's there to fret over? Gwahaha! | I12: 别担心，阿瞒！ 有我在，有什么好愁的？嘎嘎嘎！
A13: =A12 -> NODE_2 | B13: =B12+1 -> 10 | C13: =CONCATENATE(A13, "_", B13, IF(D13<>"", "_"&D13, "")) -> NODE_2_10 | E13: =VLOOKUP(F13,Overview!$A$1:$B$28,2,FALSE) -> XiahouYuan | F13: 하후연 | G13: 형님 때문에 더 걱정입니다. 저번에도 혼자 돌격하시고. | H13: It's you I worry about, brother. Charging in alone again, like last time. | I13: 我更担心的是兄长您。 上次也是一个人就冲出去了。
A14: =A13 -> NODE_2 | B14: =B13+1 -> 11 | C14: =CONCATENATE(A14, "_", B14, IF(D14<>"", "_"&D14, "")) -> NODE_2_11 | E14: =VLOOKUP(F14,Overview!$A$1:$B$28,2,FALSE) -> XiahouDun | F14: 하후돈 | G14: 뒤에서 활이나 쏘는 주제에 말이 많구나ㅋㅋ | H14: Says the one plinking arrows from the rear. Awfully talkative today, hah. | I14: 就你这躲在后头放箭的， 话还真不少呢，呵。
A15: =A14 -> NODE_2 | B15: =B14+1 -> 12 | C15: =CONCATENATE(A15, "_", B15, IF(D15<>"", "_"&D15, "")) -> NODE_2_12 | E15: =VLOOKUP(F15,Overview!$A$1:$B$28,2,FALSE) -> CaoCao | F15: 조조 | G15: 야야 가만히 있지만 말고, 니들도 나가서... | H15: Hey, hey, don't just stand there. You two get out there and... | I15: 喂喂，别光杵着， 你们俩也出去……
A16: =A15 -> NODE_2 | B16: =B15+1 -> 13 | C16: =CONCATENATE(A16, "_", B16, IF(D16<>"", "_"&D16, "")) -> NODE_2_13 | E16: Etc | G16: 주공! 성 밖에 1000여명 되는 무리들이 이 쪽을 향해 오고 있습니다! | H16: My lord! A band of a thousand or so is outside the walls, heading straight for us! | I16: 主公！ 城外有千余人的队伍， 正朝这边过来！
A17: =A16 -> NODE_2 | B17: =B16+1 -> 14 | C17: =CONCATENATE(A17, "_", B17, IF(D17<>"", "_"&D17, "")) -> NODE_2_14 | E17: =VLOOKUP(F17,Overview!$A$1:$B$28,2,FALSE) -> XiahouYuan | F17: 하후연 | G17: 호오.. | H17: Oho.. | I17: 哦……
A18: =A17 -> NODE_2 | B18: =B17+1 -> 15 | C18: =CONCATENATE(A18, "_", B18, IF(D18<>"", "_"&D18, "")) -> NODE_2_15 | E18: =VLOOKUP(F18,Overview!$A$1:$B$28,2,FALSE) -> CaoCao | F18: 조조 | G18: 음?? | H18: Hm?? | I18: 嗯？？
A19: =A18 -> NODE_2 | B19: =B18+1 -> 16 | C19: =CONCATENATE(A19, "_", B19, IF(D19<>"", "_"&D19, "")) -> NODE_2_16
A20: =A19 -> NODE_2 | B20: =B19+1 -> 17 | C20: =CONCATENATE(A20, "_", B20, IF(D20<>"", "_"&D20, "")) -> NODE_2_17 | E20: =VLOOKUP(F20,Overview!$A$1:$B$28,2,FALSE) -> CaoRen | F20: 조인 | G20: 하하하!! 맹덕 형님! 나 자효가 왔습니다!! | H20: Hahaha!! Brother Mengde! Zixiao has come!! | I20: 哈哈哈！！孟德兄！ 我子孝来了！！
A21: =A20 -> NODE_2 | B21: =B20+1 -> 18 | C21: =CONCATENATE(A21, "_", B21, IF(D21<>"", "_"&D21, "")) -> NODE_2_18 | E21: =VLOOKUP(F21,Overview!$A$1:$B$28,2,FALSE) -> XiahouDun | F21: 하후돈 | G21: 뭐야ㅋㅋ 자효잖아?ㅋ | H21: Well well, if it isn't Zixiao, heh. | I21: 哟，这不是子孝嘛，呵。
A22: =A21 -> NODE_2 | B22: =B21+1 -> 19 | C22: =CONCATENATE(A22, "_", B22, IF(D22<>"", "_"&D22, "")) -> NODE_2_19 | E22: =VLOOKUP(F22,Overview!$A$1:$B$28,2,FALSE) -> CaoCao | F22: 조조 | G22: 오오, 자효!! 이렇게 와주니 정말 고맙구만!! | H22: Oh, Zixiao!! Coming all this way, I'm truly grateful!! | I22: 哦哦，子孝！！ 你肯前来，我真是感激不尽！！
A23: =A22 -> NODE_2 | B23: =B22+1 -> 20 | C23: =CONCATENATE(A23, "_", B23, IF(D23<>"", "_"&D23, "")) -> NODE_2_20 | E23: =VLOOKUP(F23,Overview!$A$1:$B$28,2,FALSE) -> CaoRen | F23: 조인 | G23: 형님, 사적인 정은 이제 접어두겠소. | H23: Brother, I set our private ties aside from here on. | I23: 兄长，私情就到此为止吧。
A24: =A23 -> NODE_2 | B24: =B23+1 -> 21 | C24: =CONCATENATE(A24, "_", B24, IF(D24<>"", "_"&D24, "")) -> NODE_2_21 | E24: =VLOOKUP(F24,Overview!$A$1:$B$28,2,FALSE) -> CaoRen | F24: 조인 | G24: 오늘부로 저와 제 군사는 오직 주공의 명만을 따를 것이니, 천하를 바로잡아 주십시오! | H24: From this day, I and my soldiers will answer to my lord's command alone. Set the realm right, I beg you! | I24: 自今日起，我与我的兵马只听主公号令，还请您匡正天下！
A25: =A24 -> NODE_2 | B25: =B24+1 -> 22 | C25: =CONCATENATE(A25, "_", B25, IF(D25<>"", "_"&D25, "")) -> NODE_2_22 | E25: =VLOOKUP(F25,Overview!$A$1:$B$28,2,FALSE) -> CaoCao | F25: 조조 | G25: 일어나시게ㅋ 이제 곧 큰 싸움이 일어날텐데, 자효 그대의 활약을 기대하겠네. | H25: Rise, rise, heh. A great battle is coming soon, and I'll be counting on you, Zixiao. | I25: 起来吧，呵。 大战转眼便至， 子孝，我可就指望你了。
A26: =A25 -> NODE_2 | B26: =B25+1 -> 23 | C26: =CONCATENATE(A26, "_", B26, IF(D26<>"", "_"&D26, "")) -> NODE_2_23 | E26: =VLOOKUP(F26,Overview!$A$1:$B$28,2,FALSE) -> CaoRen | F26: 조인 | G26: 주공!! | H26: My lord!! | I26: 主公！！
A27: NODE_30B | B27: 0 | C27: =CONCATENATE(A27, "_", B27, IF(D27<>"", "_"&D27, "")) -> NODE_30B_0 | E27: =VLOOKUP(F27,Overview!$A$1:$B$28,2,FALSE) -> LiuBei | F27: 유비 | G27: .. 황건적을 토벌할 의용군을 모집한다?? | H27: .. Volunteers wanted to put down the Yellow Turbans?? | I27: ……招募讨伐黄巾贼的 义勇军？？
A28: =A27 -> NODE_30B | B28: =B27+1 -> 1 | C28: =CONCATENATE(A28, "_", B28, IF(D28<>"", "_"&D28, "")) -> NODE_30B_1 | E28: =VLOOKUP(F28,Overview!$A$1:$B$28,2,FALSE) -> LiuBei | F28: 유비 | G28: 에휴.. | H28: Haah.. | I28: 唉……
A29: =A28 -> NODE_30B | B29: =B28+1 -> 2 | C29: =CONCATENATE(A29, "_", B29, IF(D29<>"", "_"&D29, "")) -> NODE_30B_2 | E29: =VLOOKUP(F29,Overview!$A$1:$B$28,2,FALSE) -> ZhangFei | F29: 장비 | G29: 사내가 뭔 한숨이오?? 한심하기는! | H29: What's a man doing sighing like that?? Pathetic! | I29: 大丈夫叹什么气？？ 真是没出息！
A30: =A29 -> NODE_30B | B30: =B29+1 -> 3 | C30: =CONCATENATE(A30, "_", B30, IF(D30<>"", "_"&D30, "")) -> NODE_30B_3 | E30: =VLOOKUP(F30,Overview!$A$1:$B$28,2,FALSE) -> LiuBei | F30: 유비 | G30: 하아.. 지금 의용군에게는 뛰어난 지도자가 필요하단 말이오. | H30: Haa.. What these volunteers need right now is a fine leader. | I30: 唉……如今的义勇军， 最缺的就是一位出色的领袖。
A31: =A30 -> NODE_30B | B31: =B30+1 -> 4 | C31: =CONCATENATE(A31, "_", B31, IF(D31<>"", "_"&D31, "")) -> NODE_30B_4 | E31: =VLOOKUP(F31,Overview!$A$1:$B$28,2,FALSE) -> GuanYu | F31: 관우 | G31: ??? | H31: ??? | I31: ？？？
A32: =A31 -> NODE_30B | B32: =B31+1 -> 5 | C32: =CONCATENATE(A32, "_", B32, IF(D32<>"", "_"&D32, "")) -> NODE_30B_5 | E32: =VLOOKUP(F32,Overview!$A$1:$B$28,2,FALSE) -> LiuBei | F32: 유비 | G32: 지도자 없는 의용군은 오합지졸일 뿐.. | H32: A volunteer army with no leader is nothing but a rabble.. | I32: 没有领袖的义勇军， 不过是乌合之众……
A33: =A32 -> NODE_30B | B33: =B32+1 -> 6 | C33: =CONCATENATE(A33, "_", B33, IF(D33<>"", "_"&D33, "")) -> NODE_30B_6 | E33: =VLOOKUP(F33,Overview!$A$1:$B$28,2,FALSE) -> GuanYu | F33: 관우 | G33: 그렇다면 그대가 지도자가 되면 될 거 아니오. | H33: Then why not become that leader yourself? | I33: 那你自己当那个领袖 不就成了。
A34: =A33 -> NODE_30B | B34: =B33+1 -> 7 | C34: =CONCATENATE(A34, "_", B34, IF(D34<>"", "_"&D34, "")) -> NODE_30B_7 | E34: =VLOOKUP(F34,Overview!$A$1:$B$28,2,FALSE) -> LiuBei | F34: 유비 | G34: 나에게는 그럴 힘이 없소. | H34: I have no such strength. | I34: 我没有那样的力量。
A35: =A34 -> NODE_30B | B35: =B34+1 -> 8 | C35: =CONCATENATE(A35, "_", B35, IF(D35<>"", "_"&D35, "")) -> NODE_30B_8 | E35: =VLOOKUP(F35,Overview!$A$1:$B$28,2,FALSE) -> ZhangFei | F35: 장비 | G35: 흥! 내가 도와주겠소이다! 어디 가서 술이나 한잔 합시다. | H35: Hah! Then I'll help you! Let's go find a drink somewhere. | I35: 哼！那我来助你一把！ 找个地方喝一杯去。
A36: =A35 -> NODE_30B | B36: =B35+1 -> 9 | C36: =CONCATENATE(A36, "_", B36, IF(D36<>"", "_"&D36, "")) -> NODE_30B_9 | E36: =VLOOKUP(F36,Overview!$A$1:$B$28,2,FALSE) -> LiuBei | F36: 유비 | G36: 그럼 내가 좋은 곳을 알고 있으니, 따라 오시겠소? | H36: Then I know a fine spot. Will you follow me? | I36: 那我倒知道个好地方， 二位愿随我来吗？
A37: =A36 -> NODE_30B | B37: =B36+1 -> 10 | C37: =CONCATENATE(A37, "_", B37, IF(D37<>"", "_"&D37, "")) -> NODE_30B_10 | E37: =VLOOKUP(F37,Overview!$A$1:$B$28,2,FALSE) -> GuanYu | F37: 관우 | G37: 흠흠.. 나도 함께 가지. | H37: Ahem.. I'll come along as well. | I37: 咳咳……我也一同去吧。
A38: =A37 -> NODE_30B | B38: =B37+1 -> 11 | C38: =CONCATENATE(A38, "_", B38, IF(D38<>"", "_"&D38, "")) -> NODE_30B_11
A39: =A38 -> NODE_30B | B39: =B38+1 -> 12 | C39: =CONCATENATE(A39, "_", B39, IF(D39<>"", "_"&D39, "")) -> NODE_30B_12 | E39: =VLOOKUP(F39,Overview!$A$1:$B$28,2,FALSE) -> ZhangFei | F39: 장비 | G39: 오오! 복숭아 밭 파티장이라니ㅋ 근사하구만ㅋ | H39: Oho! A banquet in a peach orchard, heh. Very fine indeed, heh. | I39: 哦哦！竟是桃林里的酒席，呵。 够气派啊，呵。
A40: =A39 -> NODE_30B | B40: =B39+1 -> 13 | C40: =CONCATENATE(A40, "_", B40, IF(D40<>"", "_"&D40, "")) -> NODE_30B_13 | E40: =VLOOKUP(F40,Overview!$A$1:$B$28,2,FALSE) -> GuanYu | F40: 관우 | G40: 없는 살림에 너무 무리하시는게 아닐런지.. | H40: With your means so thin, isn't this rather too much.. | I40: 家底本就不厚， 这般铺张是否过了些……
A41: =A40 -> NODE_30B | B41: =B40+1 -> 14 | C41: =CONCATENATE(A41, "_", B41, IF(D41<>"", "_"&D41, "")) -> NODE_30B_14 | E41: =VLOOKUP(F41,Overview!$A$1:$B$28,2,FALSE) -> LiuBei | F41: 유비 | G41: 음.. | H41: Hm.. | I41: 嗯……
A42: =A41 -> NODE_30B | B42: =B41+1 -> 15 | C42: =CONCATENATE(A42, "_", B42, IF(D42<>"", "_"&D42, "")) -> NODE_30B_15 | E42: =VLOOKUP(F42,Overview!$A$1:$B$28,2,FALSE) -> LiuBei | F42: 유비 | G42: 한 왕실의 재건을 위해 그대들을 맞이하는 것이니 그런 소리 마시오. | H42: I welcome you both for the sake of restoring the House of Han. Say no more of it. | I42: 我是为重振汉室而迎二位， 这等话就莫要再提了。
A43: =A42 -> NODE_30B | B43: =B42+1 -> 16 | C43: =CONCATENATE(A43, "_", B43, IF(D43<>"", "_"&D43, "")) -> NODE_30B_16 | E43: =VLOOKUP(F43,Overview!$A$1:$B$28,2,FALSE) -> LiuBei | F43: 유비 | G43: 무슨 소리신지, 이 근방 돗자리는 모두 내가 납품하고 있소만. | H43: What are you saying? Every straw mat in these parts is supplied by me, you know. | I43: 这是哪里话，这一带的草席 可全是我在供货呢。
A44: =A43 -> NODE_30B | B44: =B43+1 -> 17 | C44: =CONCATENATE(A44, "_", B44, IF(D44<>"", "_"&D44, "")) -> NODE_30B_17_1 | D44: 1 | E44: =VLOOKUP(F44,Overview!$A$1:$B$28,2,FALSE) -> ZhangFei | F44: 장비 | G44: 역시 큰 뜻을 품고 있었구려ㅋ | H44: So you did harbor a great purpose after all, heh. | I44: 果然是胸怀大志之人啊，呵。
A45: =A44 -> NODE_30B | B45: =B44+1 -> 18 | C45: =CONCATENATE(A45, "_", B45, IF(D45<>"", "_"&D45, "")) -> NODE_30B_18_1 | D45: 1 | E45: =VLOOKUP(F45,Overview!$A$1:$B$28,2,FALSE) -> GuanYu | F45: 관우 | G45: 그 뜻에 동참하겠소. 형님으로 모시겠습니다. | H45: I will join you in that purpose. I shall serve you as my elder brother. | I45: 我愿追随此志。 愿奉你为兄长。
A46: =A45 -> NODE_30B | B46: =B45+1 -> 19 | C46: =CONCATENATE(A46, "_", B46, IF(D46<>"", "_"&D46, "")) -> NODE_30B_19_2 | D46: 2 | E46: =VLOOKUP(F46,Overview!$A$1:$B$28,2,FALSE) -> ZhangFei | F46: 장비 | G46: 아니!! 부자였소?? 그런데 왜 그런 거지꼴로 다녔던거요?? | H46: What!! You were rich?? Then why in the world did you go about in those rags?? | I46: 什么！！你竟是有钱人？？那 为何还整日一副乞丐模样？？
A47: =A46 -> NODE_30B | B47: =B46+1 -> 20 | C47: =CONCATENATE(A47, "_", B47, IF(D47<>"", "_"&D47, "")) -> NODE_30B_20_2 | D47: 2 | E47: =VLOOKUP(F47,Overview!$A$1:$B$28,2,FALSE) -> LiuBei | F47: 유비 | G47: 뭐 딱히.. | H47: Well, no particular reason.. | I47: 也没什么特别的……
A48: =A47 -> NODE_30B | B48: =B47+1 -> 21 | C48: =CONCATENATE(A48, "_", B48, IF(D48<>"", "_"&D48, "")) -> NODE_30B_21_2 | D48: 2 | E48: =VLOOKUP(F48,Overview!$A$1:$B$28,2,FALSE) -> GuanYu | F48: 관우 | G48: 하하하! 좋소이다! 형님으로 모실테니 큰 뜻을 품어주십시오. | H48: Hahaha! Very well! I shall serve you as my elder brother, so hold fast to that great purpose. | I48: 哈哈哈！好极了！我愿奉你 为兄长，还望你怀抱大志。
A49: =A48 -> NODE_30B | B49: =B48+1 -> 22 | C49: =CONCATENATE(A49, "_", B49, IF(D49<>"", "_"&D49, "")) -> NODE_30B_22 | E49: =VLOOKUP(F49,Overview!$A$1:$B$28,2,FALSE) -> LiuBei | F49: 유비 | G49: 고맙소. 태어난 날은 다르나 한날 한시에 죽을 것을 맹세합시다. | H49: My thanks. Though we were not born on the same day, let us swear to die on the same day and hour. | I49: 多谢二位。不求同年同月同日生， 但愿同年同月同日死。
A50: =A49 -> NODE_30B | B50: =B49+1 -> 23 | C50: =CONCATENATE(A50, "_", B50, IF(D50<>"", "_"&D50, "")) -> NODE_30B_23 | E50: =VLOOKUP(F50,Overview!$A$1:$B$28,2,FALSE) -> ZhangFei | F50: 장비 | G50: 응?? 그건 좀.. | H50: Huh?? That part's a bit much.. | I50: 啊？？这个嘛，有点……
A51: =A50 -> NODE_30B | B51: =B50+1 -> 24 | C51: =CONCATENATE(A51, "_", B51, IF(D51<>"", "_"&D51, "")) -> NODE_30B_24 | E51: =VLOOKUP(F51,Overview!$A$1:$B$28,2,FALSE) -> GuanYu | F51: 관우 | G51: 뜨거운 맹세, 영원히 변치 않을 것입니다. | H51: This burning oath, for all time, shall never be broken. | I51: 这炽热的誓言， 永世不变。
A52: =A51 -> NODE_30B | B52: =B51+1 -> 25 | C52: =CONCATENATE(A52, "_", B52, IF(D52<>"", "_"&D52, "")) -> NODE_30B_25 | E52: =VLOOKUP(F52,Overview!$A$1:$B$28,2,FALSE) -> ZhangFei | F52: 장비 | G52: 않을 것이오!! | H52: Never be broken!! | I52: 绝不会变！！
A54: NODE_16 | B54: 0 | C54: =CONCATENATE(A54, "_", B54, IF(D54<>"", "_"&D54, "")) -> NODE_16_0 | E54: =VLOOKUP(F54,Overview!$A$1:$B$28,2,FALSE) -> CaoCao | F54: 조조 | G54: ..? | H54: ..? | I54: ……？
A55: =A54 -> NODE_16 | B55: =B54+1 -> 1 | C55: =CONCATENATE(A55, "_", B55, IF(D55<>"", "_"&D55, "")) -> NODE_16_1 | E55: =VLOOKUP(F55,Overview!$A$1:$B$28,2,FALSE) -> CaoCao | F55: 조조 | G55: 뭐라고? 송헌과 위속은 전사하고, 그 서황마저 패퇴했다고? | H55: What did you say? Song Xian and Wei Xu fell in battle, and even Xu Huang was driven back? | I55: 你说什么？宋宪、魏续战死， 连徐晃也被击退了？
A56: =A55 -> NODE_16 | B56: =B55+1 -> 2 | C56: =CONCATENATE(A56, "_", B56, IF(D56<>"", "_"&D56, "")) -> NODE_16_2 | E56: =VLOOKUP(F56,Overview!$A$1:$B$28,2,FALSE) -> YanLiang | F56: 안량 | G56: 하하하! 조조놈 무장들은 어찌 이리 버러지들 뿐이더냐ㅋㅋ | H56: Hahaha! Why are Cao Cao's officers nothing but worms, heh heh. | I56: 哈哈哈！曹操手下的武将 怎么尽是些蛆虫，呵呵。
A57: =A56 -> NODE_16 | B57: =B56+1 -> 3 | C57: =CONCATENATE(A57, "_", B57, IF(D57<>"", "_"&D57, "")) -> NODE_16_3 | E57: =VLOOKUP(F57,Overview!$A$1:$B$28,2,FALSE) -> XiahouDun | F57: 하후돈 | G57: 이 자식이.. - -+ | H57: Why you little.. - -+ | I57: 你这厮…… - -+
A58: =A57 -> NODE_16 | B58: =B57+1 -> 4 | C58: =CONCATENATE(A58, "_", B58, IF(D58<>"", "_"&D58, "")) -> NODE_16_4 | E58: =VLOOKUP(F58,Overview!$A$1:$B$28,2,FALSE) -> XiahouDun | F58: 하후돈 | G58: 맹덕! 아니 주공! 내가 가서 저놈의 모가지를 따오겠소! | H58: Mengde! No, my lord! Let me go and take that man's head! | I58: 孟德！不，主公！我去把 那家伙的脑袋摘回来！
A59: =A58 -> NODE_16 | B59: =B58+1 -> 5 | C59: =CONCATENATE(A59, "_", B59, IF(D59<>"", "_"&D59, "")) -> NODE_16_5 | E59: =VLOOKUP(F59,Overview!$A$1:$B$28,2,FALSE) -> XiahouYuan | F59: 하후연 | G59: 형님! 이미 사기가 바닥입니다. 무작정 나간다고 될 일이 아니오. | H59: Brother! Morale is already at rock bottom. Charging out blindly won't settle this. | I59: 兄长！如今士气已跌到谷底。 一味莽撞出战是解决不了的。
A60: =A59 -> NODE_16 | B60: =B59+1 -> 6 | C60: =CONCATENATE(A60, "_", B60, IF(D60<>"", "_"&D60, "")) -> NODE_16_6 | E60: =VLOOKUP(F60,Overview!$A$1:$B$28,2,FALSE) -> XiahouDun | F60: 하후돈 | G60: 그럼 저 놈이 지껄이는 걸 보고만 있으란 소리냐!? | H60: So you're telling me to just stand here and listen to that dog run his mouth!? | I60: 那你是要我干站着， 听那家伙在那儿放屁吗！？
A61: =A60 -> NODE_16 | B61: =B60+1 -> 7 | C61: =CONCATENATE(A61, "_", B61, IF(D61<>"", "_"&D61, "")) -> NODE_16_7 | E61: =VLOOKUP(F61,Overview!$A$1:$B$28,2,FALSE) -> XiahouDun | F61: 하후돈 | G61: 응?? | H61: Huh?? | I61: 嗯？？
A62: =A61 -> NODE_16 | B62: =B61+1 -> 8 | C62: =CONCATENATE(A62, "_", B62, IF(D62<>"", "_"&D62, "")) -> NODE_16_8 | E62: =VLOOKUP(F62,Overview!$A$1:$B$28,2,FALSE) -> CaoCao | F62: 조조 | G62: 어찌한다.. | H62: What to do.. | I62: 该如何是好……
A63: =A62 -> NODE_16 | B63: =B62+1 -> 9 | C63: =CONCATENATE(A63, "_", B63, IF(D63<>"", "_"&D63, "")) -> NODE_16_9 | E63: =VLOOKUP(F63,Overview!$A$1:$B$28,2,FALSE) -> GuanYu | F63: 관우 | G63: 곤란하신 일이 있으신가봅니다, 조조님. | H63: You seem to be in some difficulty, Lord Cao Cao. | I63: 看来您正为难，曹操大人。
A64: =A63 -> NODE_16 | B64: =B63+1 -> 10 | C64: =CONCATENATE(A64, "_", B64, IF(D64<>"", "_"&D64, "")) -> NODE_16_10 | E64: =VLOOKUP(F64,Overview!$A$1:$B$28,2,FALSE) -> ZhangLiao | F64: 장료 | G64: 와주셨군요, 관 장군! | H64: You've come, General Guan! | I64: 关将军，您来了！
A65: =A64 -> NODE_16 | B65: =B64+1 -> 11 | C65: =CONCATENATE(A65, "_", B65, IF(D65<>"", "_"&D65, "")) -> NODE_16_11 | E65: =VLOOKUP(F65,Overview!$A$1:$B$28,2,FALSE) -> ZhangLiao | F65: 장료 | G65: 주군, 제가 관 장군과 함께 급습해 보겠습니다. | H65: My lord, allow me to strike alongside General Guan. | I65: 主公，请让我与关将军 一同奇袭。
A66: =A65 -> NODE_16 | B66: =B65+1 -> 12 | C66: =CONCATENATE(A66, "_", B66, IF(D66<>"", "_"&D66, "")) -> NODE_16_12 | E66: =VLOOKUP(F66,Overview!$A$1:$B$28,2,FALSE) -> CaoCao | F66: 조조 | G66: (공을 세우게 하고 싶진 않지만..) | H66: (I'd rather not hand him the merit, but..) | I66: （我并不想让他立功，可是……）
... A100: =A99 -> NODE_16 | B100: =B99+1 -> 46 | C100: =CONCATENATE(A100, "_", B100, IF(D100<>"", "_"&D100, "")) -> NODE_16_46 | E100: =VLOOKUP(F100,Overview!$A$1:$B$28,2,FALSE) -> GuanYu | F100: 관우 | G100: 애꾸놈의 기를 확실히 꺾어주지. 이 자의 목을 걸어두고 함성을 질러라!! | H100: I'll break that one-eyed fool's spirit for good. Hang this head high and let out a roar!! | I100: 定要彻底折了那独眼的锐气。 把此人的首级挂起来，放声呐喊！！
A101: =A100 -> NODE_16 | B101: =B100+1 -> 47 | C101: =CONCATENATE(A101, "_", B101, IF(D101<>"", "_"&D101, "")) -> NODE_16_47_1 | D101: 1 | E101: =VLOOKUP(F101,Overview!$A$1:$B$28,2,FALSE) -> LiuBei | F101: 유비 | G101: 관우는 내가 여기 있는 것을 모를 것입니다. | H101: Guan Yu will not know that I am here. | I101: 关羽应当不知道 我在此处。
A102: =A101 -> NODE_16 | B102: =B101+1 -> 48 | C102: =CONCATENATE(A102, "_", B102, IF(D102<>"", "_"&D102, "")) -> NODE_16_48_1 | D102: 1 | E102: =VLOOKUP(F102,Overview!$A$1:$B$28,2,FALSE) -> LiuBei | F102: 유비 | G102: 제가 직접 관우에게 밀사를 보내겠습니다. 그렇다면 관우는 바로 달려올 것입니다. | H102: I shall send a secret envoy to Guan Yu myself. If I do, he will come at once. | I102: 我亲自派密使去见关羽。 如此一来，他必定立刻赶来。
A103: =A102 -> NODE_16 | B103: =B102+1 -> 49 | C103: =CONCATENATE(A103, "_", B103, IF(D103<>"", "_"&D103, "")) -> NODE_16_49_1 | D103: 1 | E103: =VLOOKUP(F103,Overview!$A$1:$B$28,2,FALSE) -> YuanShao | F103: 원소 | G103: .. | H103: .. | I103: ……
A104: =A103 -> NODE_16 | B104: =B103+1 -> 50 | C104: =CONCATENATE(A104, "_", B104, IF(D104<>"", "_"&D104, "")) -> NODE_16_50_1 | D104: 1 | E104: =VLOOKUP(F104,Overview!$A$1:$B$28,2,FALSE) -> LiuBei | F104: 유비 | G104: 안량, 문추를 잃은 것은 안타까운 일입니다. | H104: Losing Yan Liang and Wen Chou is a grievous thing. | I104: 折了颜良、文丑， 实在令人痛惜。
A105: =A104 -> NODE_16 | B105: =B104+1 -> 51 | C105: =CONCATENATE(A105, "_", B105, IF(D105<>"", "_"&D105, "")) -> NODE_16_51_1 | D105: 1 | E105: =VLOOKUP(F105,Overview!$A$1:$B$28,2,FALSE) -> LiuBei | F105: 유비 | G105: 허나, 관우를 얻는 것은 천하를 얻는 것과 다름이 없을 것입니다! | H105: Yet gaining Guan Yu would be no different from gaining the realm itself! | I105: 然而得到关羽， 与得天下并无二致！
A106: =A105 -> NODE_16 | B106: =B105+1 -> 52 | C106: =CONCATENATE(A106, "_", B106, IF(D106<>"", "_"&D106, "")) -> NODE_16_52_1 | D106: 1 | E106: =VLOOKUP(F106,Overview!$A$1:$B$28,2,FALSE) -> YuanShao | F106: 원소 | G106: 하하하. 내가 뭐 그리 소인배도 아니고ㅋㅋ | H106: Hahaha. I'm hardly such a small-minded man, heh heh. | I106: 哈哈哈。我又不是什么 小肚鸡肠之辈，呵呵。
A107: =A106 -> NODE_16 | B107: =B106+1 -> 53 | C107: =CONCATENATE(A107, "_", B107, IF(D107<>"", "_"&D107, "")) -> NODE_16_53_1 | D107: 1 | E107: =VLOOKUP(F107,Overview!$A$1:$B$28,2,FALSE) -> YuanShao | F107: 원소 | G107: 오늘 밤 관우를 맞이하는 술잔을 기울이도록 하지ㅋ | H107: Tonight we shall raise our cups to welcome Guan Yu, heh. | I107: 今夜便举杯， 为迎关羽接风，呵。
A108: =A107 -> NODE_16 | B108: =B107+1 -> 54 | C108: =CONCATENATE(A108, "_", B108, IF(D108<>"", "_"&D108, "")) -> NODE_16_54_1 | D108: 1 | E108: =VLOOKUP(F108,Overview!$A$1:$B$28,2,FALSE) -> LiuBei | F108: 유비 | G108: 관우.. 살아 있었구나.. | H108: Guan Yu.. so you were alive.. | I108: 关羽……你还活着……
A109: =A108 -> NODE_16 | B109: =B108+1 -> 55 | C109: =CONCATENATE(A109, "_", B109, IF(D109<>"", "_"&D109, "")) -> NODE_16_55_2 | D109: 2 | E109: =VLOOKUP(F109,Overview!$A$1:$B$28,2,FALSE) -> YuanShao | F109: 원소 | G109: .. | H109: .. | I109: ……
A110: =A109 -> NODE_16 | B110: =B109+1 -> 56 | C110: =CONCATENATE(A110, "_", B110, IF(D110<>"", "_"&D110, "")) -> NODE_16_56_2 | D110: 2 | E110: =VLOOKUP(F110,Overview!$A$1:$B$28,2,FALSE) -> LiuBei | F110: 유비 | G110: .. 관우야?? | H110: .. Guan Yu?? | I110: ……关羽？？
A111: =A110 -> NODE_16 | B111: =B110+1 -> 57 | C111: =CONCATENATE(A111, "_", B111, IF(D111<>"", "_"&D111, "")) -> NODE_16_57_2 | D111: 2 | E111: =VLOOKUP(F111,Overview!$A$1:$B$28,2,FALSE) -> YuanShao | F111: 원소 | G111: 유비.. 네 놈 때문에 내가 제일 아끼는 무장 두명을 잃었다. | H111: Liu Bei.. because of you I have lost the two officers I prized most. | I111: 刘备……因为你，我折了 最器重的两名武将。
A112: =A111 -> NODE_16 | B112: =B111+1 -> 58 | C112: =CONCATENATE(A112, "_", B112, IF(D112<>"", "_"&D112, "")) -> NODE_16_58_2 | D112: 2 | E112: =VLOOKUP(F112,Overview!$A$1:$B$28,2,FALSE) -> LiuBei | F112: 유비 | G112: 아니 죽인 것은 관우인데요? 그게 아니라. 제가 지금 당장 밀서를.. | H112: But it was Guan Yu who killed them? No, that aside. Let me send a secret letter at once.. | I112: 可杀他们的是关羽啊？ 不是，我是说，我这就修书一封……
... A119: =A118 -> NODE_16 | B119: =B118+1 -> 65 | C119: =CONCATENATE(A119, "_", B119, IF(D119<>"", "_"&D119, "")) -> NODE_16_65_2 | D119: 2 | E119: =VLOOKUP(F119,Overview!$A$1:$B$28,2,FALSE) -> GuanYu | F119: 관우 | G119: 흐음.. 갑자기 형님이 그립군.. | H119: Hmm.. suddenly I find myself missing my brother.. | I119: 嗯……忽然有些想念兄长了……
A121: NODE_27 | B121: 0 | C121: =CONCATENATE(A121, "_", B121, IF(D121<>"", "_"&D121, "")) -> NODE_27_0 | E121: =VLOOKUP(F121,Overview!$A$1:$B$28,2,FALSE) -> GuanYu | F121: 관우 | G121: 뭐라고? 방금 뭐라고 하셨소!? | H121: What did you say? Say that again!? | I121: 你说什么？刚才说了什么！？
A122: NODE_27 | B122: =B121+1 -> 1 | C122: =CONCATENATE(A122, "_", B122, IF(D122<>"", "_"&D122, "")) -> NODE_27_1 | E122: =VLOOKUP(F122,Overview!$A$1:$B$28,2,FALSE) -> ZhangLiao | F122: 장료 | G122: 원소군에 의탁해 있던 유비님이 원소에 의해 처형당했다 합니다. | H122: They say Lord Liu Bei, who had taken shelter with Yuan Shao's army, was executed by Yuan Shao. | I122: 据说寄身于袁绍军中的刘备大人， 已被袁绍处死。
A123: NODE_27 | B123: =B122+1 -> 2 | C123: =CONCATENATE(A123, "_", B123, IF(D123<>"", "_"&D123, "")) -> NODE_27_2 | E123: =VLOOKUP(F123,Overview!$A$1:$B$28,2,FALSE) -> GuanYu | F123: 관우 | G123: 서..설마.. 내가 안량과 문추를 베어서.. 인가?? | H123: Could.. could it be.. because I cut down Yan Liang and Wen Chou?? | I123: 难……难道说……是因为我斩了 颜良与文丑……吗？？
A124: NODE_27 | B124: =B123+1 -> 3 | C124: =CONCATENATE(A124, "_", B124, IF(D124<>"", "_"&D124, "")) -> NODE_27_3 | E124: =VLOOKUP(F124,Overview!$A$1:$B$28,2,FALSE) -> GuanYu | F124: 관우 | G124: 흑흑.. 형님.. ㅜㅜ | H124: Sob.. brother.. T_T | I124: 呜呜……兄长……呜呜
A125: NODE_27 | B125: =B124+1 -> 4 | C125: =CONCATENATE(A125, "_", B125, IF(D125<>"", "_"&D125, "")) -> NODE_27_4 | E125: =VLOOKUP(F125,Overview!$A$1:$B$28,2,FALSE) -> GuanYu | F125: 관우 | G125: 한날 한시에 죽겠다는 맹세, 결코 헛되지 않을 것이오! | H125: Our oath to die on the same day and hour shall not be in vain! | I125: 同年同月同日死的誓言， 绝不会白许！
A126: NODE_27 | B126: =B125+1 -> 5 | C126: =CONCATENATE(A126, "_", B126, IF(D126<>"", "_"&D126, "")) -> NODE_27_5 | E126: =VLOOKUP(F126,Overview!$A$1:$B$28,2,FALSE) -> ZhangLiao | F126: 장료 | G126: 앗! 관 장군! | H126: Ah! General Guan! | I126: 啊！关将军！
A127: NODE_27 | B127: =B126+1 -> 6 | C127: =CONCATENATE(A127, "_", B127, IF(D127<>"", "_"&D127, "")) -> NODE_27_6 | E127: =VLOOKUP(F127,Overview!$A$1:$B$28,2,FALSE) -> CaoCao | F127: 조조 | G127: 관공!! | H127: Lord Guan!! | I127: 关公！！
A128: NODE_27 | B128: =B127+1 -> 7 | C128: =CONCATENATE(A128, "_", B128, IF(D128<>"", "_"&D128, "")) -> NODE_27_7 | E128: =VLOOKUP(F128,Overview!$A$1:$B$28,2,FALSE) -> CaoCao | F128: 조조 | G128: 어찌 이리 어리석은! | H128: How can you be so foolish! | I128: 怎能如此愚昧！
A129: NODE_27 | B129: =B128+1 -> 8 | C129: =CONCATENATE(A129, "_", B129, IF(D129<>"", "_"&D129, "")) -> NODE_27_8 | E129: =VLOOKUP(F129,Overview!$A$1:$B$28,2,FALSE) -> GuanYu | F129: 관우 | G129: 조조님. 그대에겐 이미 공을 세워 빚을 다 갚았다 생각하오. | H129: Lord Cao Cao. I consider my debt to you repaid in full through the merits I have won. | I129: 曹操大人。我以立下的功劳， 已将欠你的恩情尽数偿清。
A130: NODE_27 | B130: =B129+1 -> 9 | C130: =CONCATENATE(A130, "_", B130, IF(D130<>"", "_"&D130, "")) -> NODE_27_9 | E130: =VLOOKUP(F130,Overview!$A$1:$B$28,2,FALSE) -> GuanYu | F130: 관우 | G130: 그대는 그대의 일을 하시오. | H130: You go about your business. | I130: 你做你的事去吧。
A131: NODE_27 | B131: =B130+1 -> 10 | C131: =CONCATENATE(A131, "_", B131, IF(D131<>"", "_"&D131, "")) -> NODE_27_10 | E131: =VLOOKUP(F131,Overview!$A$1:$B$28,2,FALSE) -> CaoCao | F131: 조조 | G131: 어찌 그런 소리를 하시는거요? | H131: How can you speak that way? | I131: 你怎能说出这样的话？
A132: NODE_27 | B132: =B131+1 -> 11 | C132: =CONCATENATE(A132, "_", B132, IF(D132<>"", "_"&D132, "")) -> NODE_27_11 | E132: =VLOOKUP(F132,Overview!$A$1:$B$28,2,FALSE) -> GuanYu | F132: 관우 | G132: 유비 형님이 안계신 이상 한 왕실의 운명도 여기까지요. | H132: With Brother Liu Bei gone, the fate of the House of Han ends here as well. | I132: 刘备兄长已不在， 汉室的命数也到此为止了。
A133: NODE_27 | B133: =B132+1 -> 12 | C133: =CONCATENATE(A133, "_", B133, IF(D133<>"", "_"&D133, "")) -> NODE_27_12 | E133: =VLOOKUP(F133,Overview!$A$1:$B$28,2,FALSE) -> CaoCao | F133: 조조 | G133: 나를 도와 한 왕실을 부흥시키고, 천하를 안정토록 하면 될 것 아니오? | H133: Then help me restore the House of Han and bring peace to the realm. Would that not do? | I133: 那便助我重振汉室， 安定天下，不也一样吗？
... A159: NODE_27 | B159: =B158+1 -> 38 | C159: =CONCATENATE(A159, "_", B159, IF(D159<>"", "_"&D159, "")) -> NODE_27_38 | E159: =VLOOKUP(F159,Overview!$A$1:$B$28,2,FALSE) -> CaoCao | F159: 조조 | G159: 그..그렇게 하시오.. | H159: Do.. do as you will.. | I159: 就……就依你所言吧……
A161: NODE_28 | B161: 0 | C161: =CONCATENATE(A161, "_", B161, IF(D161<>"", "_"&D161, "")) -> NODE_28_0 | E161: =VLOOKUP(F161,Overview!$A$1:$B$28,2,FALSE) -> ZhangLiao | F161: 장료 | G161: 과연 대단하십니다, 관 장군. | H161: Magnificent indeed, General Guan. | I161: 实在了得，关将军。
A162: =A161 -> NODE_28 | B162: =B161+1 -> 1 | C162: =CONCATENATE(A162, "_", B162, IF(D162<>"", "_"&D162, "")) -> NODE_28_1 | E162: =VLOOKUP(F162,Overview!$A$1:$B$28,2,FALSE) -> ZhangLiao | F162: 장료 | G162: 하북 지역을 1년 만에 평정하시고, 쉬지도 않은 채 곧바로 형주 정벌이라니.. | H162: Pacifying all of Hebei in a single year, and then straight on to the conquest of Jingzhou without even resting.. | I162: 一年之内平定河北， 不曾歇息便直取荆州……
A163: =A162 -> NODE_28 | B163: =B162+1 -> 2 | C163: =CONCATENATE(A163, "_", B163, IF(D163<>"", "_"&D163, "")) -> NODE_28_2 | E163: =VLOOKUP(F163,Overview!$A$1:$B$28,2,FALSE) -> GuanYu | F163: 관우 | G163: 죄책감이 날 짓눌러 견딜 수가 없소. 멈출 수가 없구려. | H163: The guilt crushes me; I cannot bear it. I cannot stop. | I163: 罪恶感压得我难以承受。 我停不下来。
A164: =A163 -> NODE_28 | B164: =B163+1 -> 3 | C164: =CONCATENATE(A164, "_", B164, IF(D164<>"", "_"&D164, "")) -> NODE_28_3 | E164: =VLOOKUP(F164,Overview!$A$1:$B$28,2,FALSE) -> XiahouDun | F164: 하후돈 | G164: 하하하. 역시 관형이오. 대단하십니다! | H164: Hahaha. Brother Guan, as ever. Magnificent! | I164: 哈哈哈。还是关兄啊。 了得！
A165: =A164 -> NODE_28 | B165: =B164+1 -> 4 | C165: =CONCATENATE(A165, "_", B165, IF(D165<>"", "_"&D165, "")) -> NODE_28_4 | E165: =VLOOKUP(F165,Overview!$A$1:$B$28,2,FALSE) -> GuanYu | F165: 관우 | G165: .. | H165: .. | I165: ……
A166: =A165 -> NODE_28 | B166: =B165+1 -> 5 | C166: =CONCATENATE(A166, "_", B166, IF(D166<>"", "_"&D166, "")) -> NODE_28_5 | E166: =VLOOKUP(F166,Overview!$A$1:$B$28,2,FALSE) -> XiahouDun | F166: 하후돈 | G166: 하하;; | H166: Haha;; | I166: 哈哈;;
A167: =A166 -> NODE_28 | B167: =B166+1 -> 6 | C167: =CONCATENATE(A167, "_", B167, IF(D167<>"", "_"&D167, "")) -> NODE_28_6 | E167: =VLOOKUP(F167,Overview!$A$1:$B$28,2,FALSE) -> XiahouDun | F167: 하후돈 | G167: 쳇.. 무안하게시리.. - _- | H167: Tch.. talk about awkward.. - _- | I167: 切……真够尴尬的…… - _-
...

Sheet String_Story
A1: #Type | B1: #Mission Key | C1: #Value | D1: key | E1: kr | F1: en | G1: cn
A2: string | B2: string | C2: string | D2: string | E2: string | F2: string | G2: string
A3: TITLE | B3: node_1 | D3: =UPPER(B3)&"_TITLE" -> NODE_1_TITLE | E3: 황천당립 | F3: The Yellow Heaven Shall Rise | G3: 黄天当立
A4: TITLE | B4: node_2 | D4: =UPPER(B4)&"_TITLE" -> NODE_2_TITLE | E4: 철벽 | F4: Iron Wall | G4: 铁壁
A5: TITLE | B5: node_3 | D5: =UPPER(B5)&"_TITLE" -> NODE_3_TITLE | E5: 호로관 전투 | F5: Battle of Hulao Gate | G5: 虎牢关之战
A6: TITLE | B6: node_4 | D6: =UPPER(B6)&"_TITLE" -> NODE_4_TITLE | E6: 호랑이의 몰락 | F6: Fall of the Tiger | G6: 猛虎陨落
A7: TITLE | B7: node_5 | D7: =UPPER(B7)&"_TITLE" -> NODE_5_TITLE | E7: 한실의 기둥 | F7: Pillar of the Han | G7: 汉室之柱
A8: TITLE | B8: node_6 | D8: =UPPER(B8)&"_TITLE" -> NODE_6_TITLE | E8: 서주학살 | F8: The Xuzhou Massacre | G8: 徐州屠城
A9: TITLE | B9: node_7 | D9: =UPPER(B9)&"_TITLE" -> NODE_7_TITLE | E9: 서주구원 | F9: The Rescue of Xuzhou | G9: 徐州驰援
A10: TITLE | B10: node_8 | D10: =UPPER(B10)&"_TITLE" -> NODE_8_TITLE | E10: 담보가 된 옥 | F10: The Jade Held in Pledge | G10: 作为抵押的玉玺
A11: TITLE | B11: node_9 | D11: =UPPER(B11)&"_TITLE" -> NODE_9_TITLE | E11: 미주랑 | F11: Zhou the Handsome | G11: 美周郎
A12: TITLE | B12: node_10 | D12: =UPPER(B12)&"_TITLE" -> NODE_10_TITLE | E12: 칠척극 | F12: The Seven-Foot Halberd | G12: 七尺戟
A13: TITLE | B13: node_11 | D13: =UPPER(B13)&"_TITLE" -> NODE_11_TITLE | E13: 헌제 옹립 | F13: Enthroning Emperor Xian | G13: 拥立献帝
A14: TITLE | B14: node_12a | D14: =UPPER(B14)&"_TITLE" -> NODE_12A_TITLE | E14: 백호 사냥 A | F14: White Tiger Hunt A | G14: 白虎狩猎 A
... A40: TITLE | B40: node_31 | D40: =UPPER(B40)&"_TITLE" -> NODE_31_TITLE | E40: 최종장 | F40: The Final Chapter | G40: 最终章
A41: DESC | B41: node_1 | D41: =UPPER(B41)&"_DESC" -> NODE_1_DESC | E41: "천하를 뒤덮은 거대한 광기와 혼란" | F41: "A vast madness and chaos smothering the realm" | G41: “席卷天下的滔天狂乱”
A42: DESC | B42: node_2 | D42: =UPPER(B42)&"_DESC" -> NODE_2_DESC | E42: "뚫리지 않는 방패" | F42: "A shield that will not be pierced" | G42: “无法穿透的盾”
A43: DESC | B43: node_3 | D43: =UPPER(B43)&"_DESC" -> NODE_3_DESC | E43: "절대적 공포가 선사한 압도적인 무력감" | F43: "The crushing helplessness that absolute terror brings" | G43: “绝对的恐惧带来的压倒性无力感”
A44: DESC | B44: node_4 | D44: =UPPER(B44)&"_DESC" -> NODE_4_DESC | E44: "무너지는 강동의 호랑이" | F44: "The Tiger of Jiangdong falls" | G44: “倒下的江东之虎”
A45: DESC | B45: node_5 | D45: =UPPER(B45)&"_DESC" -> NODE_5_DESC | E45: "나의 장자방이로다" | F45: "This man is my Zhang Zifang" | G45: “此乃吾之子房也”
A46: DESC | B46: node_6 | D46: =UPPER(B46)&"_DESC" -> NODE_6_DESC | E46: "붉은 피로 물들이다" | F46: "Stained crimson with blood" | G46: “以鲜血染红大地”
A47: DESC | B47: node_7 | D47: =UPPER(B47)&"_DESC" -> NODE_7_DESC | E47: "거대한 폭력에 맞선 신념" | F47: "Conviction standing against overwhelming violence" | G47: “直面滔天暴力的信念”
A48: DESC | B48: node_8 | D48: =UPPER(B48)&"_DESC" -> NODE_8_DESC | E48: "강동의 소패왕 날개를 펴다" | F48: "The Little Conqueror of Jiangdong spreads his wings" | G48: “江东小霸王展翅”
A49: DESC | B49: node_9 | D49: =UPPER(B49)&"_DESC" -> NODE_9_DESC | E49: "천하보다 뜨거운 두 영웅의 의리" | F49: "A bond between two heroes hotter than the realm itself" | G49: “比天下更炽热的两位英雄之义”
A50: DESC | B50: node_10 | D50: =UPPER(B50)&"_DESC" -> NODE_10_DESC | E50: "주군을 찾는 전사의 눈" | F50: "A warrior's eyes, searching for a lord" | G50: “寻觅主公的战士之眼”
A51: DESC | B51: node_11 | D51: =UPPER(B51)&"_DESC" -> NODE_11_DESC | E51: "처절한 피난길의 끝은 난세의 영웅" | F51: "At the end of a desperate flight stands the hero of a broken age" | G51: “凄绝逃亡之路的尽头，是乱世的英雄”
A52: DESC | B52: node_12a | D52: =UPPER(B52)&"_DESC" -> NODE_12A_DESC | E52: "소패왕의 자비 없는 진격" | F52: "The Little Conqueror's merciless advance" | G52: “小霸王毫无慈悲的进军”
... A78: DESC | B78: node_31 | D78: =UPPER(B78)&"_DESC" -> NODE_31_DESC | E78: "무신은 무신을 위하여" | F78: "The god of war, for the god of war" | G78: “武神，为武神而战”
A79: CHOICE | B79: node_1 | C79: 1 | D79: =UPPER(B79)&"_CHOICE_"&C79 -> NODE_1_CHOICE_1
A80: CHOICE | B80: node_1 | C80: 2 | D80: =UPPER(B80)&"_CHOICE_"&C80 -> NODE_1_CHOICE_2
A81: CHOICE | B81: node_5 | C81: 1 | D81: =UPPER(B81)&"_CHOICE_"&C81 -> NODE_5_CHOICE_1
A82: CHOICE | B82: node_5 | C82: 2 | D82: =UPPER(B82)&"_CHOICE_"&C82 -> NODE_5_CHOICE_2
A83: CHOICE | B83: node_6 | C83: 1 | D83: =UPPER(B83)&"_CHOICE_"&C83 -> NODE_6_CHOICE_1
A84: CHOICE | B84: node_6 | C84: 2 | D84: =UPPER(B84)&"_CHOICE_"&C84 -> NODE_6_CHOICE_2
A85: CHOICE | B85: node_7 | C85: 1 | D85: =UPPER(B85)&"_CHOICE_"&C85 -> NODE_7_CHOICE_1
A86: CHOICE | B86: node_7 | C86: 2 | D86: =UPPER(B86)&"_CHOICE_"&C86 -> NODE_7_CHOICE_2
A87: CHOICE | B87: node_10 | C87: 1 | D87: =UPPER(B87)&"_CHOICE_"&C87 -> NODE_10_CHOICE_1
A88: CHOICE | B88: node_10 | C88: 2 | D88: =UPPER(B88)&"_CHOICE_"&C88 -> NODE_10_CHOICE_2
A89: CHOICE | B89: node_12b | C89: 1 | D89: =UPPER(B89)&"_CHOICE_"&C89 -> NODE_12B_CHOICE_1
A90: CHOICE | B90: node_12b | C90: 2 | D90: =UPPER(B90)&"_CHOICE_"&C90 -> NODE_12B_CHOICE_2
... A94: CHOICE | B94: node_15 | C94: 2 | D94: =UPPER(B94)&"_CHOICE_"&C94 -> NODE_15_CHOICE_2
A95: CHOICE | B95: node_16 | C95: 1 | D95: =UPPER(B95)&"_CHOICE_"&C95 -> NODE_16_CHOICE_1 | E95: 이 정도면 빚은 갚은거겠지. 이제 돌아가볼까? | F95: That should settle the debt. Shall I head back now? | G95: 这样也算还清恩情了吧。 该回去了吗？
A96: CHOICE | B96: node_16 | C96: 2 | D96: =UPPER(B96)&"_CHOICE_"&C96 -> NODE_16_CHOICE_2 | E96: 애꾸놈의 기를 확실히 꺾어주지. 이 자의 목을 걸어두고 함성을 질러라!! | F96: I'll break that one-eyed fool's spirit for good. Hang this head high and let out a roar!! | G96: 定要彻底折了那独眼的锐气。 把此人的首级挂起来，放声呐喊！！
A97: CHOICE | B97: node_19b | C97: 1 | D97: =UPPER(B97)&"_CHOICE_"&C97 -> NODE_19B_CHOICE_1
A98: CHOICE | B98: node_19b | C98: 2 | D98: =UPPER(B98)&"_CHOICE_"&C98 -> NODE_19B_CHOICE_2
A99: CHOICE | B99: node_21b | C99: 1 | D99: =UPPER(B99)&"_CHOICE_"&C99 -> NODE_21B_CHOICE_1
A100: CHOICE | B100: node_21b | C100: 2 | D100: =UPPER(B100)&"_CHOICE_"&C100 -> NODE_21B_CHOICE_2
A101: CHOICE | B101: node_25 | C101: 1 | D101: =UPPER(B101)&"_CHOICE_"&C101 -> NODE_25_CHOICE_1
A102: CHOICE | B102: node_25 | C102: 2 | D102: =UPPER(B102)&"_CHOICE_"&C102 -> NODE_25_CHOICE_2
A103: CHOICE_DESC | B103: node_1 | C103: 1 | D103: =UPPER(B103)&"_CHOICE_"&C103&"_DESC" -> NODE_1_CHOICE_1_DESC | E103: ="선택"&C103 -> 선택1 | F103: Choice 1 | G103: 选项1
A104: CHOICE_DESC | B104: node_1 | C104: 2 | D104: =UPPER(B104)&"_CHOICE_"&C104&"_DESC" -> NODE_1_CHOICE_2_DESC | E104: ="선택"&C104 -> 선택2 | F104: Choice 2 | G104: 选项2
A105: CHOICE_DESC | B105: node_5 | C105: 1 | D105: =UPPER(B105)&"_CHOICE_"&C105&"_DESC" -> NODE_5_CHOICE_1_DESC | E105: ="선택"&C105 -> 선택1 | F105: Choice 1 | G105: 选项1
A106: CHOICE_DESC | B106: node_5 | C106: 2 | D106: =UPPER(B106)&"_CHOICE_"&C106&"_DESC" -> NODE_5_CHOICE_2_DESC | E106: ="선택"&C106 -> 선택2 | F106: Choice 2 | G106: 选项2
A107: CHOICE_DESC | B107: node_6 | C107: 1 | D107: =UPPER(B107)&"_CHOICE_"&C107&"_DESC" -> NODE_6_CHOICE_1_DESC | E107: ="선택"&C107 -> 선택1 | F107: Choice 1 | G107: 选项1
A108: CHOICE_DESC | B108: node_6 | C108: 2 | D108: =UPPER(B108)&"_CHOICE_"&C108&"_DESC" -> NODE_6_CHOICE_2_DESC | E108: ="선택"&C108 -> 선택2 | F108: Choice 2 | G108: 选项2
A109: CHOICE_DESC | B109: node_7 | C109: 1 | D109: =UPPER(B109)&"_CHOICE_"&C109&"_DESC" -> NODE_7_CHOICE_1_DESC | E109: ="선택"&C109 -> 선택1 | F109: Choice 1 | G109: 选项1
A110: CHOICE_DESC | B110: node_7 | C110: 2 | D110: =UPPER(B110)&"_CHOICE_"&C110&"_DESC" -> NODE_7_CHOICE_2_DESC | E110: ="선택"&C110 -> 선택2 | F110: Choice 2 | G110: 选项2
A111: CHOICE_DESC | B111: node_10 | C111: 1 | D111: =UPPER(B111)&"_CHOICE_"&C111&"_DESC" -> NODE_10_CHOICE_1_DESC | E111: ="선택"&C111 -> 선택1 | F111: Choice 1 | G111: 选项1
A112: CHOICE_DESC | B112: node_10 | C112: 2 | D112: =UPPER(B112)&"_CHOICE_"&C112&"_DESC" -> NODE_10_CHOICE_2_DESC | E112: ="선택"&C112 -> 선택2 | F112: Choice 2 | G112: 选项2
A113: CHOICE_DESC | B113: node_12b | C113: 1 | D113: =UPPER(B113)&"_CHOICE_"&C113&"_DESC" -> NODE_12B_CHOICE_1_DESC | E113: ="선택"&C113 -> 선택1 | F113: Choice 1 | G113: 选项1
A114: CHOICE_DESC | B114: node_12b | C114: 2 | D114: =UPPER(B114)&"_CHOICE_"&C114&"_DESC" -> NODE_12B_CHOICE_2_DESC | E114: ="선택"&C114 -> 선택2 | F114: Choice 2 | G114: 选项2
... A118: CHOICE_DESC | B118: node_15 | C118: 2 | D118: =UPPER(B118)&"_CHOICE_"&C118&"_DESC" -> NODE_15_CHOICE_2_DESC | E118: ="선택"&C118 -> 선택2 | F118: Choice 2 | G118: 选项2
A119: CHOICE_DESC | B119: node_16 | C119: 1 | D119: =UPPER(B119)&"_CHOICE_"&C119&"_DESC" -> NODE_16_CHOICE_1_DESC | E119: 눈에 띄는 건 싫군 | F119: I'd rather not stand out | G119: 不想太惹眼
A120: CHOICE_DESC | B120: node_16 | C120: 2 | D120: =UPPER(B120)&"_CHOICE_"&C120&"_DESC" -> NODE_16_CHOICE_2_DESC | E120: 문추의 목을 높이 들어라 | F120: Raise Wen Chou's head high | G120: 把文丑的首级高高举起
A121: CHOICE_DESC | B121: node_19b | C121: 1 | D121: =UPPER(B121)&"_CHOICE_"&C121&"_DESC" -> NODE_19B_CHOICE_1_DESC | E121: ="선택"&C121 -> 선택1 | F121: Choice 1 | G121: 选项1
A122: CHOICE_DESC | B122: node_19b | C122: 2 | D122: =UPPER(B122)&"_CHOICE_"&C122&"_DESC" -> NODE_19B_CHOICE_2_DESC | E122: ="선택"&C122 -> 선택2 | F122: Choice 2 | G122: 选项2
A123: CHOICE_DESC | B123: node_21b | C123: 1 | D123: =UPPER(B123)&"_CHOICE_"&C123&"_DESC" -> NODE_21B_CHOICE_1_DESC | E123: ="선택"&C123 -> 선택1 | F123: Choice 1 | G123: 选项1
A124: CHOICE_DESC | B124: node_21b | C124: 2 | D124: =UPPER(B124)&"_CHOICE_"&C124&"_DESC" -> NODE_21B_CHOICE_2_DESC | E124: ="선택"&C124 -> 선택2 | F124: Choice 2 | G124: 选项2
A125: CHOICE_DESC | B125: node_25 | C125: 1 | D125: =UPPER(B125)&"_CHOICE_"&C125&"_DESC" -> NODE_25_CHOICE_1_DESC | E125: ="선택"&C125 -> 선택1 | F125: Choice 1 | G125: 选项1
A126: CHOICE_DESC | B126: node_25 | C126: 2 | D126: =UPPER(B126)&"_CHOICE_"&C126&"_DESC" -> NODE_25_CHOICE_2_DESC | E126: ="선택"&C126 -> 선택2 | F126: Choice 2 | G126: 选项2

Sheet String_GuideQuest
A1: #Type | B1: #Mission Key | C1: #Value | D1: key | E1: kr | F1: en | G1: cn
A2: string | B2: string | C2: string | D2: string | E2: string | F2: string | G2: string
A3: TITLE | B3: GUIDE | C3: MOVE | D3: =B3&"_"&TEXT(C3,"0000")&"_"&A3 -> GUIDE_MOVE_TITLE | E3: 이동하기 | F3: Move | G3: 移动
A4: =A3 -> TITLE | B4: =B3 -> GUIDE | C4: NORMAL_ATTACK | D4: =B4&"_"&TEXT(C4,"0000")&"_"&A4 -> GUIDE_NORMAL_ATTACK_TITLE | E4: 기본공격 하기 | F4: Basic Attack | G4: 普通攻击
A5: =A4 -> TITLE | B5: =B4 -> GUIDE | C5: MAIN_SKILL_USE | D5: =B5&"_"&TEXT(C5,"0000")&"_"&A5 -> GUIDE_MAIN_SKILL_USE_TITLE | E5: 스킬 사용하기 | F5: Use a Skill | G5: 使用技能
A6: =A5 -> TITLE | B6: =B5 -> GUIDE | C6: DASH_USE | D6: =B6&"_"&TEXT(C6,"0000")&"_"&A6 -> GUIDE_DASH_USE_TITLE | E6: 대쉬 사용하기 | F6: Use Dash | G6: 使用冲刺
A7: =A6 -> TITLE | B7: =B6 -> GUIDE | C7: STORYMODE_PLAY | D7: =B7&"_"&TEXT(C7,"0000")&"_"&A7 -> GUIDE_STORYMODE_PLAY_TITLE | E7: 스토리모드 클리어 | F7: Clear Story Mode | G7: 通关剧情模式
A8: =A7 -> TITLE | B8: =B7 -> GUIDE | C8: CHARACTER_DEPLOY | D8: =B8&"_"&TEXT(C8,"0000")&"_"&A8 -> GUIDE_CHARACTER_DEPLOY_TITLE | E8: 장수 배치하기 | F8: Deploy Officers | G8: 部署武将
A9: =A8 -> TITLE | B9: =B8 -> GUIDE | C9: DAILY_DUNGEON_PLAY | D9: =B9&"_"&TEXT(C9,"0000")&"_"&A9 -> GUIDE_DAILY_DUNGEON_PLAY_TITLE | E9: 요일 던전 클리어 | F9: Clear the Daily Dungeon | G9: 通关每日副本
A10: =A9 -> TITLE | B10: REPEAT | C10: ENEMY_KILL | D10: =B10&"_"&TEXT(C10,"0000")&"_"&A10 -> REPEAT_ENEMY_KILL_TITLE | E10: 적 처치하기 | F10: Defeat Enemies | G10: 击败敌人
A11: =A10 -> TITLE | B11: REPEAT | C11: TOURNAMENT_PLAY | D11: =B11&"_"&TEXT(C11,"0000")&"_"&A11 -> REPEAT_TOURNAMENT_PLAY_TITLE | E11: 비무대회 참여하기 | F11: Join a Tournament | G11: 参加比武大会
A12: =A11 -> TITLE | B12: REPEAT | C12: RAID_PLAY | D12: =B12&"_"&TEXT(C12,"0000")&"_"&A12 -> REPEAT_RAID_PLAY_TITLE | E12: 레이드 참여하기 | F12: Join a Raid | G12: 参加讨伐战
A13: =A12 -> TITLE | B13: REPEAT | C13: GACHA_PROGRESS | D13: =B13&"_"&TEXT(C13,"0000")&"_"&A13 -> REPEAT_GACHA_PROGRESS_TITLE | E13: 장수 모집 진행하기 | F13: Recruit Officers | G13: 进行武将招募
A14: =A13 -> TITLE | B14: REPEAT | C14: FARM_RICE_EARN | D14: =B14&"_"&TEXT(C14,"0000")&"_"&A14 -> REPEAT_FARM_RICE_EARN_TITLE | E14: 군량 수확하기 | F14: Harvest Provisions | G14: 收获军粮
A15: =A14 -> TITLE | B15: REPEAT | C15: MARKET_GOLD_EARN | D15: =B15&"_"&TEXT(C15,"0000")&"_"&A15 -> REPEAT_MARKET_GOLD_EARN_TITLE | E15: 금화 수확하기 | F15: Collect Gold | G15: 收取金币
A16: =A15 -> TITLE | B16: REPEAT | C16: OFFICE_MISSION_PROGRESS | D16: =B16&"_"&TEXT(C16,"0000")&"_"&A16 -> REPEAT_OFFICE_MISSION_PROGRESS_TITLE | E16: 관아 파견 보내기 | F16: Send an Office Mission | G16: 派遣官府任务
A17: =A16 -> TITLE | B17: REPEAT | C17: DAILY_DUNGEON_PLAY | D17: =B17&"_"&TEXT(C17,"0000")&"_"&A17 -> REPEAT_DAILY_DUNGEON_PLAY_TITLE | E17: 요일던전 플레이하기 | F17: Play the Daily Dungeon | G17: 游玩每日副本
A18: =A17 -> TITLE | B18: REPEAT | C18: STAGE_BOSS_KILL | D18: =B18&"_"&TEXT(C18,"0000")&"_"&A18 -> REPEAT_STAGE_BOSS_KILL_TITLE | E18: 스테이지 보스 처치 | F18: Defeat the Stage Boss | G18: 击败关卡首领
A19: DESC | B19: GUIDE | C19: MOVE | D19: =B19&"_"&TEXT(C19,"0000")&"_"&A19 -> GUIDE_MOVE_DESC | E19: [W,A,S,D]를 눌러\n이동해보자. | F19: Press [W,A,S,D] and try moving. | G19: 按[W,A,S,D]键， 试着移动一下吧。
A20: DESC_MOBILE | B20: GUIDE | C20: MOVE | D20: =B20&"_"&TEXT(C20,"0000")&"_"&A20 -> GUIDE_MOVE_DESC_MOBILE | E20: 화면을 터치해 이동해보자. | F20: Tap the screen to move. | G20: 点击屏幕移动看看吧。
A21: DESC | B21: =B19 -> GUIDE | C21: NORMAL_ATTACK | D21: =B21&"_"&TEXT(C21,"0000")&"_"&A21 -> GUIDE_NORMAL_ATTACK_DESC | E21: [X]키를 눌러 공격해보자.\n화면을 터치해도 가능해. | F21: Press [X] to attack. Tapping the screen works too. | G21: 按[X]键攻击试试。 点击屏幕也可以哦。
A22: DESC_MOBILE | B22: =B21 -> GUIDE | C22: NORMAL_ATTACK | D22: =B22&"_"&TEXT(C22,"0000")&"_"&A22 -> GUIDE_NORMAL_ATTACK_DESC_MOBILE | E22: 공격 버튼을 눌러보자. | F22: Try the attack button. | G22: 按一下攻击按钮吧。
A23: DESC | B23: =B22 -> GUIDE | C23: MAIN_SKILL_USE | D23: =B23&"_"&TEXT(C23,"0000")&"_"&A23 -> GUIDE_MAIN_SKILL_USE_DESC | E23: [C]키를 누른 후 좌클릭해봐.\n버튼을 눌러서도 가능해. | F23: Press [C], then left-click. The button works too. | G23: 按下[C]键后点击左键。 用按钮也可以哦。
A24: DESC_MOBILE | B24: =B23 -> GUIDE | C24: MAIN_SKILL_USE | D24: =B24&"_"&TEXT(C24,"0000")&"_"&A24 -> GUIDE_MAIN_SKILL_USE_DESC_MOBILE | E24: 스킬 버튼을 눌러보자. | F24: Try the skill button. | G24: 按一下技能按钮吧。
A25: DESC | B25: =B23 -> GUIDE | C25: DASH_USE | D25: =B25&"_"&TEXT(C25,"0000")&"_"&A25 -> GUIDE_DASH_USE_DESC | E25: [SpaceBar]키를 눌러보자.\n버튼을 눌러서도 가능해. | F25: Try pressing [SpaceBar]. The button works too. | G25: 试着按[空格]键。 用按钮也可以哦。
A26: DESC_MOBILE | B26: =B24 -> GUIDE | C26: DASH_USE | D26: =B26&"_"&TEXT(C26,"0000")&"_"&A26 -> GUIDE_DASH_USE_DESC_MOBILE | E26: 대쉬 버튼을 눌러보자. | F26: Try the dash button. | G26: 按一下冲刺按钮吧。
A27: DESC | B27: =B25 -> GUIDE | C27: STORYMODE_PLAY | D27: =B27&"_"&TEXT(C27,"0000")&"_"&A27 -> GUIDE_STORYMODE_PLAY_DESC | E27: 스토리 모드를 진행해서\n동료를 얻자! | F27: Play through Story Mode and gain allies! | G27: 进行剧情模式， 获得伙伴吧！
A28: DESC | B28: =B27 -> GUIDE | C28: CHARACTER_DEPLOY | D28: =B28&"_"&TEXT(C28,"0000")&"_"&A28 -> GUIDE_CHARACTER_DEPLOY_DESC | E28: 얻은 장수를 배치하자! | F28: Deploy the officers you've gained! | G28: 把获得的武将部署上阵吧！
A29: DESC | B29: =B28 -> GUIDE | C29: DAILY_DUNGEON_PLAY | D29: =B29&"_"&TEXT(C29,"0000")&"_"&A29 -> GUIDE_DAILY_DUNGEON_PLAY_DESC
A30: DESC | B30: REPEAT | C30: ENEMY_KILL | D30: =B30&"_"&TEXT(C30,"0000")&"_"&A30 -> REPEAT_ENEMY_KILL_DESC
A31: DESC | B31: REPEAT | C31: TOURNAMENT_PLAY | D31: =B31&"_"&TEXT(C31,"0000")&"_"&A31 -> REPEAT_TOURNAMENT_PLAY_DESC
A32: DESC | B32: REPEAT | C32: RAID_PLAY | D32: =B32&"_"&TEXT(C32,"0000")&"_"&A32 -> REPEAT_RAID_PLAY_DESC
A33: DESC | B33: REPEAT | C33: GACHA_PROGRESS | D33: =B33&"_"&TEXT(C33,"0000")&"_"&A33 -> REPEAT_GACHA_PROGRESS_DESC
A34: DESC | B34: REPEAT | C34: FARM_RICE_EARN | D34: =B34&"_"&TEXT(C34,"0000")&"_"&A34 -> REPEAT_FARM_RICE_EARN_DESC
A35: DESC | B35: REPEAT | C35: MARKET_GOLD_EARN | D35: =B35&"_"&TEXT(C35,"0000")&"_"&A35 -> REPEAT_MARKET_GOLD_EARN_DESC
A36: DESC | B36: REPEAT | C36: OFFICE_MISSION_PROGRESS | D36: =B36&"_"&TEXT(C36,"0000")&"_"&A36 -> REPEAT_OFFICE_MISSION_PROGRESS_DESC
A37: DESC | B37: REPEAT | C37: DAILY_DUNGEON_PLAY | D37: =B37&"_"&TEXT(C37,"0000")&"_"&A37 -> REPEAT_DAILY_DUNGEON_PLAY_DESC
A38: DESC | B38: REPEAT | C38: STAGE_BOSS_KILL | D38: =B38&"_"&TEXT(C38,"0000")&"_"&A38 -> REPEAT_STAGE_BOSS_KILL_DESC

Sheet String_Quest
A1: #Type | B1: #Mission Key | C1: #Value | D1: key | E1: kr | F1: en | G1: cn
A2: string | B2: string | C2: string | D2: string | E2: string | F2: string | G2: string
D3: CATEGORY_NAME_DAILY | E3: 일일 임무 | F3: Daily Quests | G3: 每日任务
D4: CATEGORY_NAME_WEEKLY | E4: 주간 임무 | F4: Weekly Quests | G4: 每周任务
D5: CATEGORY_NAME_SEASON | E5: 기간 임무 | F5: Seasonal Quests | G5: 限期任务
C6: login | D6: =UPPER(C6)&"_NAME" -> LOGIN_NAME | E6: 로그인 | F6: Log In | G6: 登录
C7: enemy_kill | D7: =UPPER(C7)&"_NAME" -> ENEMY_KILL_NAME | E7: 적 처치하기 | F7: Defeat Enemies | G7: 击败敌人
C8: tournament_play | D8: =UPPER(C8)&"_NAME" -> TOURNAMENT_PLAY_NAME | E8: 비무대회 | F8: Tournament | G8: 比武大会
C9: raid_play | D9: =UPPER(C9)&"_NAME" -> RAID_PLAY_NAME | E9: 레이드 | F9: Raid | G9: 讨伐战
C10: gacha_proceed | D10: =UPPER(C10)&"_NAME" -> GACHA_PROCEED_NAME | E10: 연회 | F10: Banquet | G10: 宴会
C11: rice_claim | D11: =UPPER(C11)&"_NAME" -> RICE_CLAIM_NAME | E11: 군량 수확 | F11: Harvest Provisions | G11: 收获军粮
C12: Gold_Claim | D12: =UPPER(C12)&"_NAME" -> GOLD_CLAIM_NAME | E12: 금화 수확 | F12: Collect Gold | G12: 收取金币
C13: office_dispatch | D13: =UPPER(C13)&"_NAME" -> OFFICE_DISPATCH_NAME | E13: 관아 파견 | F13: Office Mission | G13: 官府派遣
C14: daily_dungeon_play | D14: =UPPER(C14)&"_NAME" -> DAILY_DUNGEON_PLAY_NAME | E14: 요일 던전 | F14: Daily Dungeon | G14: 每日副本
C15: stage_boss_kill | D15: =UPPER(C15)&"_NAME" -> STAGE_BOSS_KILL_NAME | E15: 대장 적 처치 | F15: Defeat the Stage Boss | G15: 击败关卡首领
C16: ads_watch | D16: =UPPER(C16)&"_NAME" -> ADS_WATCH_NAME | E16: 광고 시청 | F16: Watch an Ad | G16: 观看广告
C17: item_buy | D17: =UPPER(C17)&"_NAME" -> ITEM_BUY_NAME | E17: 상품 구매 | F17: Purchase Goods | G17: 购买商品
C18: item_use | D18: =UPPER(C18)&"_NAME" -> ITEM_USE_NAME | E18: 아이템 사용 | F18: Use an Item | G18: 使用道具
D19: STATUS_COMPLETE | E19: 완료 | F19: Complete | G19: 已完成
C20: login | D20: =UPPER(C20)&"_DESC" -> LOGIN_DESC | E20: 로그인을 하세요. | F20: Log in. | G20: 请登录。
C21: enemy_kill | D21: =UPPER(C21)&"_DESC" -> ENEMY_KILL_DESC | E21: {0} 적을 처치하세요. | F21: Defeat {0} enemies. | G21: 击败{0}名敌人。
C22: tournament_play | D22: =UPPER(C22)&"_DESC" -> TOURNAMENT_PLAY_DESC | E22: {0} 비무대회에 참가하세요. | F22: Join a Tournament {0} times. | G22: 参加比武大会{0}次。
C23: raid_play | D23: =UPPER(C23)&"_DESC" -> RAID_PLAY_DESC | E23: {0} 레이드에 참여하세요. | F23: Join a Raid {0} times. | G23: 参加讨伐战{0}次。
C24: gacha_proceed | D24: =UPPER(C24)&"_DESC" -> GACHA_PROCEED_DESC | E24: 연회를 여세요. | F24: Hold a Banquet. | G24: 举办宴会。
C25: rice_claim | D25: =UPPER(C25)&"_DESC" -> RICE_CLAIM_DESC | E25: 영지 농장에서 군량을 수확하세요. | F25: Harvest provisions at the domain farmland. | G25: 在领地农田收获军粮。
C26: Gold_Claim | D26: =UPPER(C26)&"_DESC" -> GOLD_CLAIM_DESC | E26: 영지 시장에서 금화를 수확하세요. | F26: Collect gold at the domain market. | G26: 在领地市场收取金币。
C27: office_dispatch | D27: =UPPER(C27)&"_DESC" -> OFFICE_DISPATCH_DESC | E27: 영지 관아에서 {0} 파견보내세요. | F27: Send {0} missions at the domain office. | G27: 在领地官府派遣{0}次。
C28: daily_dungeon_play | D28: =UPPER(C28)&"_DESC" -> DAILY_DUNGEON_PLAY_DESC | E28: {0} 요일던전에 참여하세요. | F28: Enter the Daily Dungeon {0} times. | G28: 参加每日副本{0}次。
C29: stage_boss_kill | D29: =UPPER(C29)&"_DESC" -> STAGE_BOSS_KILL_DESC | E29: {0} 대장 적을 처치하세요. | F29: Defeat {0} stage bosses. | G29: 击败{0}名关卡首领。
C30: ads_watch | D30: =UPPER(C30)&"_DESC" -> ADS_WATCH_DESC | E30: 광고를 시청하세요. | F30: Watch an ad. | G30: 请观看广告。
C31: item_buy | D31: =UPPER(C31)&"_DESC" -> ITEM_BUY_DESC | E31: 아이템을 구매하세요. | F31: Purchase an item. | G31: 请购买道具。
C32: item_use | D32: =UPPER(C32)&"_DESC" -> ITEM_USE_DESC | E32: 아이템을 사용하세요. | F32: Use an item. | G32: 请使用道具。
D33: CATEGORY_NAME_S_DAILY | E33: 일일 임무 | F33: DAILY | G33: 每日任务
D34: CATEGORY_NAME_S_WEEKLY | E34: 주간 임무 | F34: WEEKLY | G34: 每周任务

Sheet String_Traits
A1: #key | B1: key | C1: kr | D1: en | E1: cn
A2: string | B2: string | C2: string | D2: string | E2: string
A3: leadership | B3: =UPPER(A3) & "_DESC" -> LEADERSHIP_DESC | C3: 통솔 | D3: Leadership | E3: 统率
A4: strength | B4: =UPPER(A4) & "_DESC" -> STRENGTH_DESC | C4: 무력 | D4: Strength | E4: 武力
A5: intellect | B5: =UPPER(A5) & "_DESC" -> INTELLECT_DESC | C5: 지력 | D5: Intellect | E5: 智力
A6: politics | B6: =UPPER(A6) & "_DESC" -> POLITICS_DESC | C6: 정치 | D6: Politics | E6: 政治
A7: charisma | B7: =UPPER(A7) & "_DESC" -> CHARISMA_DESC | C7: 매력 | D7: Charisma | E7: 魅力
A8: attack_power | B8: =UPPER(A8) & "_DESC" -> ATTACK_POWER_DESC | C8: 공격력 | D8: Attack Power | E8: 攻击力
A9: defence | B9: =UPPER(A9) & "_DESC" -> DEFENCE_DESC | C9: 방어력 | D9: Defense | E9: 防御力
A10: attack_speed | B10: =UPPER(A10) & "_DESC" -> ATTACK_SPEED_DESC | C10: 공격속도 | D10: Attack Speed | E10: 攻击速度
A11: health_max | B11: =UPPER(A11) & "_DESC" -> HEALTH_MAX_DESC | C11: 체력 | D11: Health | E11: 生命值
A12: move_speed | B12: =UPPER(A12) & "_DESC" -> MOVE_SPEED_DESC | C12: 이동속도 | D12: Move Speed | E12: 移动速度
A13: life_steal | B13: =UPPER(A13) & "_DESC" -> LIFE_STEAL_DESC | C13: 체력흡수 | D13: Lifesteal | E13: 生命汲取
A14: critical_rate | B14: =UPPER(A14) & "_DESC" -> CRITICAL_RATE_DESC | C14: 치명타율 | D14: Critical Rate | E14: 暴击率
... A27: def_effect_damage_taken_reduced | B27: =UPPER(A27) & "_DESC" -> DEF_EFFECT_DAMAGE_TAKEN_REDUCED_DESC | C27: 피격 시 {0}%확률로 받는 피해량 {1}% 감소 | D27: {0}% chance when hit to reduce damage taken by {1}% | E27: 受击时有{0}%概率使受到的伤害降低{1}%
A28: leadership | B28: =UPPER(A28) & "_TITLE" -> LEADERSHIP_TITLE | C28: 통솔 | D28: Leadership | E28: 统率
A29: strength | B29: =UPPER(A29) & "_TITLE" -> STRENGTH_TITLE | C29: 무력 | D29: Strength | E29: 武力
A30: intellect | B30: =UPPER(A30) & "_TITLE" -> INTELLECT_TITLE | C30: 지력 | D30: Intellect | E30: 智力
A31: politics | B31: =UPPER(A31) & "_TITLE" -> POLITICS_TITLE | C31: 정치 | D31: Politics | E31: 政治
A32: charisma | B32: =UPPER(A32) & "_TITLE" -> CHARISMA_TITLE | C32: 매력 | D32: Charisma | E32: 魅力
A33: attack_power | B33: =UPPER(A33) & "_TITLE" -> ATTACK_POWER_TITLE | C33: 공격력 | D33: Attack Power | E33: 攻击力
A34: defence | B34: =UPPER(A34) & "_TITLE" -> DEFENCE_TITLE | C34: 방어력 | D34: Defense | E34: 防御力
A35: attack_speed | B35: =UPPER(A35) & "_TITLE" -> ATTACK_SPEED_TITLE | C35: 공격속도 | D35: Attack Speed | E35: 攻击速度
A36: health_max | B36: =UPPER(A36) & "_TITLE" -> HEALTH_MAX_TITLE | C36: 체력 | D36: Health | E36: 生命值
A37: move_speed | B37: =UPPER(A37) & "_TITLE" -> MOVE_SPEED_TITLE | C37: 이동속도 | D37: Move Speed | E37: 移动速度
A38: life_steal | B38: =UPPER(A38) & "_TITLE" -> LIFE_STEAL_TITLE | C38: 체력흡수 | D38: Lifesteal | E38: 生命汲取
A39: critical_rate | B39: =UPPER(A39) & "_TITLE" -> CRITICAL_RATE_TITLE | C39: 치명타율 | D39: Critical Rate | E39: 暴击率
... A52: def_effect_damage_taken_reduced | B52: =UPPER(A52) & "_TITLE" -> DEF_EFFECT_DAMAGE_TAKEN_REDUCED_TITLE | C52: 피격시 피해량 감소 | D52: Damage Reduction on Hit | E52: 受击时降低伤害
B53: INVALID_GRADE | C53: [{0}] 등급 달성시 해제 | D53: Unlocks at [{0}] | E53: 达到 [{0}] 解锁
B54: VALID_OPEN | C54: 특성 새로 부여 가능 | D54: Reroll Available | E54: 可重置属性

Sheet String_Alert
A1: #key | B1: key | C1: kr | D1: en | E1: cn
A2: string | B2: string | C2: string | D2: string | E2: string
B3: AD_COMPLETE | C3: 광고 시청 완료 | D3: Ad Watched | E3: 广告观看完毕
B4: ALL_RECEIVE_REWARD | C4: 보상을 모두 수령했습니다. | D4: All rewards claimed. | E4: 已领取全部奖励。
B5: ALREADY_MAX_GRADE | C5: 이미 최고 등급입니다. | D5: Already at the highest grade. | E5: 已是最高品阶。
B6: ALREADY_MAX_LEVEL | C6: 이미 최고 레벨입니다. | D6: Already at max level. | E6: 已是最高等级。
B7: ALREADY_RUN_UPGRADE | C7: 이미 업그레이드가 진행중입니다. | D7: An upgrade is already in progress. | E7: 升级已在进行中。
B8: BUY_FAILED | C8: 구매 실패 | D8: Purchase Failed | E8: 购买失败
B9: CAN_NOT_SKIP | C9: 건너뛰기할 수 없습니다. | D9: Cannot skip. | E9: 无法跳过。
B10: CASTLE_READY_UPGRADE_OFFICE | C10: 관아 업그레이드 준비완료! | D10: The office is ready to upgrade! | E10: 官府升级准备完成！
B11: CASTLE_CATCH_THIEF | C11: 도적을 잡았습니다! | D11: Bandit caught! | E11: 抓住盗贼了！
B12: CASTLE_CLAIM | C12: [{0}] {1}개 수령했습니다. | D12: Claimed {1} [{0}]. | E12: 已领取[{0}] {1}个。
B13: CASTLE_FINISH_THIEF | C13: 영지에서 도적이 도망갔습니다! | D13: The bandit escaped your domain! | E13: 盗贼从领地逃走了！
B14: CASTLE_FULL_BATCH_HERO | C14: 배치 인원이 이미 모두 찼습니다. | D14: All deployment slots are full. | E14: 部署人数已满。
... B68: INVALID_CHANGE_LANGUAGE | C68: 지금은 언어를 변경할 수 없습니다. | D68: You cannot change the language right now. | E68: 当前无法更改语言。
B69: MODAL_MOVE_SHOP | C69: 상점으로 이동하시겠습니까?
B70: MODAL_BUY | C70: 구매하시겠습니까?
B71: MODAL_BUY_CURRENCY_NOT_ENOUGH | C71: {0} 부족합니다.\n구매하시겠습니까?
B72: MODAL_BUY_ITEM | C72: {0}\n구매하시겠습니까?
B73: BUY_SUCCESS | C73: 구매 성공
